Workbook

Sheet README
A1: DecisionOS -> SaaS-Stable Tracker
A2: Sprint plan + Kanban board covering every fix from the backend, schema/scale, and AI/Brain reviews, ending in DevOps + Data Migration.
A3: Generated 2026-08-04 · Branch: Backend_optimization · Source docs: docs/BACKEND_SAAS_READINESS_REVIEW.md, docs/BACKEND_SCHEMA_SCALE_GOLIVE_REVIEW.md, docs/AI_BRAIN_AGENTIC_REVIEW.md
A5: How to use this workbook
A6: • | B6: Dashboard — live rollup of every sprint AND the Testing Plan: task counts, % complete, open P0s, and the overall go-live gate status. All formulas — edit Status on Task Backlog / Testing Plan and this updates itself.
A7: • | B7: Task Backlog — the single source of truth for engineering work. One row per fix. Change the Status dropdown as work moves; this drives the Dashboard and is the sortable/filterable 'sprint sheet.'
A8: • | B8: Kanban Board — visual board grouped by Sprint (the swimlanes), cards color-coded by Priority. Snapshot view for planning conversations; the Task Backlog is what you actually edit day to day.
A9: • | B9: Testing Plan — every test type required before going live (automated, multi-tenant isolation, security, load/performance, resilience, migration/backup) PLUS the Alpha -> Closed Beta -> Staged Beta -> GA rollout milestones with entry/exit criteria for each stage.
A10: • | B10: Go-Live Checklist — the final gate. Every row must be checked TRUE before opening self-serve signup or onboarding client #1 at scale — includes a line item confirming every Testing Plan phase passed.
A11: • | B11: RBAC & People Access — product-level audit of who-can-do-what. Companion to Sprint 2. Backlog items RBAC-01..30 also mirrored into Task Backlog under sprint 'Sprint 2.5' / 'Sprint 3' / 'Sprint 4' / 'Sprint 5'.
A13: Legend — Priority
A14: P0 | B14: Ship-blocker — must close before the next tenant / go-live gate it sits in
A15: P1 | B15: Fix before selling to a real customer — not an immediate blocker but close soon
A16: P2 | B16: Quality/hardening — schedule once P0/P1 are clear
A18: Legend — Status
A19: Backlog
A20: To Do
A21: In Progress
A22: Blocked
A23: In Review
A24: Done
A26: Cells to edit
A27: On Task Backlog: Status, Owner, Start Date, Due Date, and Notes are yours to fill in / update. On Testing Plan: Status and Owner are yours to update. On Go-Live Checklist: set Done? to TRUE only once verified. All editable columns are shown with a gold header fill. Everything else documents the finding and should not need editing.

Sheet Dashboard
B2: Go-Live Readiness Dashboard
B3: Everything below recalculates from Task Backlog — update Status there, not here.
B5: Total tasks | C5: =COUNTA('Task Backlog'!A2:A84)
B6: Done | C6: =COUNTIF('Task Backlog'!J2:J84,"Done")
B7: Overall % complete | C7: =IFERROR(C6/C5,0)
B8: Open P0s (all sprints) | C8: =COUNTIFS('Task Backlog'!F2:F84,"P0",'Task Backlog'!J2:J84,"<>Done")
B9: Go-Live blockers still open | C9: =COUNTIFS('Task Backlog'!N2:N84,"Yes",'Task Backlog'!J2:J84,"<>Done")
B10: Testing Plan phases not yet Passed | C10: =COUNTIF('Testing Plan'!I13:I33,"<>Passed")
B12: READY FOR 100-CLIENT SaaS? | C12: =IF(AND(C9=0,C10=0),"READY — all go-live blockers closed and every testing phase passed","NOT READY — "&C9&" blocker(s) open, "&C10&" testing phase(s) not yet Passed")
B14: Sprint | C14: Goal | D14: Gate? | E14: Total | F14: Done | G14: % Complete | H14: Open P0s
B15: Sprint 0 — Critical Security & Auth | C15: Close every exploit that would get the platform owned in week one. No external tenant before this is clear. | D15: GATE | E15: =COUNTIF('Task Backlog'!B2:B84,"Sprint 0") | F15: =COUNTIFS('Task Backlog'!B2:B84,"Sprint 0",'Task Backlog'!J2:J84,"Done") | G15: =IFERROR(F15/E15,0) | H15: =COUNTIFS('Task Backlog'!B2:B84,"Sprint 0",'Task Backlog'!F2:F84,"P0",'Task Backlog'!J2:J84,"<>Done")
B16: Sprint 1 — Scale & Operational Blockers | C16: Fix the operational issues that break under multiple replicas / real concurrent load. | D16: GATE | E16: =COUNTIF('Task Backlog'!B2:B84,"Sprint 1") | F16: =COUNTIFS('Task Backlog'!B2:B84,"Sprint 1",'Task Backlog'!J2:J84,"Done") | G16: =IFERROR(F16/E16,0) | H16: =COUNTIFS('Task Backlog'!B2:B84,"Sprint 1",'Task Backlog'!F2:F84,"P0",'Task Backlog'!J2:J84,"<>Done")
B17: Sprint 2 — Tenancy Hygiene & Data Integrity | C17: Harden tenant isolation edges and fix data-integrity rough spots found in the schema audit. | D17: Parallel | E17: =COUNTIF('Task Backlog'!B2:B84,"Sprint 2") | F17: =COUNTIFS('Task Backlog'!B2:B84,"Sprint 2",'Task Backlog'!J2:J84,"Done") | G17: =IFERROR(F17/E17,0) | H17: =COUNTIFS('Task Backlog'!B2:B84,"Sprint 2",'Task Backlog'!F2:F84,"P0",'Task Backlog'!J2:J84,"<>Done")
B18: Sprint 3 — Billing & Multi-Tenant AI Keys | C18: Stand up real billing and per-tenant AI cost isolation — required before charging money. | D18: GATE | E18: =COUNTIF('Task Backlog'!B2:B84,"Sprint 3") | F18: =COUNTIFS('Task Backlog'!B2:B84,"Sprint 3",'Task Backlog'!J2:J84,"Done") | G18: =IFERROR(F18/E18,0) | H18: =COUNTIFS('Task Backlog'!B2:B84,"Sprint 3",'Task Backlog'!F2:F84,"P0",'Task Backlog'!J2:J84,"<>Done")
B19: Sprint 4 — AI Brain / Agentic Enhancement | C19: Upgrade retrieval to real RAG and the Brain toward agentic. Parallel track — does not block go-live. | D19: Parallel | E19: =COUNTIF('Task Backlog'!B2:B84,"Sprint 4") | F19: =COUNTIFS('Task Backlog'!B2:B84,"Sprint 4",'Task Backlog'!J2:J84,"Done") | G19: =IFERROR(F19/E19,0) | H19: =COUNTIFS('Task Backlog'!B2:B84,"Sprint 4",'Task Backlog'!F2:F84,"P0",'Task Backlog'!J2:J84,"<>Done")
B20: Sprint 5 — DevOps, Deployment & Data Migration | C20: Final gate: staging, load test, observability, tested backups, migration plan, staged rollout, go/no-go. | D20: GATE | E20: =COUNTIF('Task Backlog'!B2:B84,"Sprint 5") | F20: =COUNTIFS('Task Backlog'!B2:B84,"Sprint 5",'Task Backlog'!J2:J84,"Done") | G20: =IFERROR(F20/E20,0) | H20: =COUNTIFS('Task Backlog'!B2:B84,"Sprint 5",'Task Backlog'!F2:F84,"P0",'Task Backlog'!J2:J84,"<>Done")

Sheet Task Backlog
A1: ID | B1: Sprint | C1: Category | D1: Task | E1: Fix / Description | F1: Priority | G1: Source Doc | H1: File Reference | I1: Effort (S/M/L) | J1: Status | K1: Owner | L1: Start Date | M1: Due Date | N1: Blocks Go-Live? | O1: Notes
A2: S0-01 | B2: Sprint 0 | C2: Security/Auth | D2: Remove hardcoded superadmin default credentials | E2: Require env vars for SUPERADMIN_EMAIL/PASSWORD; stop overwriting DB hash on every restart so rotation works | F2: P0 | G2: SaaS Readiness Review | H2: server.py:4925-4937 | I2: S | J2: Done | L2: 2026-08-11 | M2: 2026-08-11 | N2: Yes | O2: Shipped in FIX-006-A (c57b550).
A3: S0-02 | B3: Sprint 0 | C3: Security/Auth | D3: Fix CORS wildcard + credentials | E3: Replace allow_origin_regex='.*' with a strict origin allow-list; add CSRF protection for cookie-authed mutating routes | F3: P0 | G3: SaaS Readiness Review | H3: server.py:4994-5001, core.py:218-222 | I3: M | J3: Done | L3: 2026-08-12 | M3: 2026-08-12 | N3: Yes | O3: Shipped in FIX-006-B (ababc06).
A4: S0-03 | B4: Sprint 0 | C4: Security/Auth | D4: Auth-gate file downloads | E4: Add get_current_user + tenant ownership check to GET /api/files/{fname}; currently unauth, guessable UUID = any tenant's file | F4: P0 | G4: SaaS Readiness Review | H4: server.py:3032-3038 | I4: S | J4: Done | L4: 2026-08-12 | M4: 2026-08-12 | N4: Yes | O4: Shipped in FIX-006-C (685141d).
A5: S0-04 | B5: Sprint 0 | C5: Security/Auth | D5: Kill dev-mode OTP leak | E5: Stop returning dev_otp in the API response; hard-fail boot if no SMS provider configured when ENV=prod | F5: P0 | G5: SaaS Readiness Review | H5: server.py:1345-1347 | I5: S | J5: Done | L5: 2026-08-12 | M5: 2026-08-12 | N5: Yes | O5: Shipped in FIX-006-C (685141d).
A6: S0-05 | B6: Sprint 0 | C6: Security/Auth | D6: Fix WhatsApp signature bypass | E6: Reject the webhook request on HMAC mismatch instead of logging + processing anyway | F6: P0 | G6: SaaS Readiness Review | H6: server.py:3919-3933 | I6: S | J6: Done | L6: 2026-08-12 | M6: 2026-08-12 | N6: Yes | O6: Shipped in FIX-006-C (685141d).
A7: S0-06 | B7: Sprint 0 | C7: Security/Auth | D7: Rate-limit + captcha unauth AI endpoints | E7: Add Turnstile/hCaptcha + IP rate limit to /api/signup/* and /api/onboarding/* — currently unauth and can burn unlimited LLM spend | F7: P0 | G7: SaaS Readiness Review | H7: routers/signup.py, routers/onboarding.py:39,73 | I7: M | J7: Done | L7: 2026-08-12 | M7: 2026-08-12 | N7: Yes | O7: Shipped in FIX-006-D (93a9f1c).
A8: S0-07 | B8: Sprint 0 | C8: Security/Auth | D8: Add login rate limiting | E8: Tenant user login has no attempt lockout (admin login does); add 5-attempt/15-min lockout to match | F8: P1 | G8: SaaS Readiness Review | H8: routers/auth.py:151-162 | I8: S | J8: Done | L8: 2026-08-12 | M8: 2026-08-12 | N8: Yes | O8: Shipped in FIX-006-D (93a9f1c).
A9: S0-08 | B9: Sprint 0 | C9: Security/Auth | D9: Stop returning raw JWT in response body | E9: Login/register return the token in JSON as well as the cookie; any XSS bypasses HttpOnly. Cookie-only. | F9: P1 | G9: SaaS Readiness Review | H9: routers/auth.py:148,162 | I9: S | J9: Done | L9: 2026-08-11 | M9: 2026-08-11 | N9: Yes | O9: Shipped in FIX-006-A (c57b550).
A10: S0-09 | B10: Sprint 0 | C10: Security/Auth | D10: Split JWT secret: tenant vs platform admin | E10: Single JWT_SECRET used for both; only the 'type' claim separates them. Use two secrets. | F10: P1 | G10: SaaS Readiness Review | H10: core.py:237,297 | I10: S | J10: Done | L10: 2026-08-11 | M10: 2026-08-11 | N10: Yes | O10: Shipped in FIX-006-A (c57b550).
A11: S0-10 | B11: Sprint 0 | C11: Security/Auth | D11: Invalidate invite tokens after use | E11: Invite tokens never expire after first use; invite_start also bypasses OTP cooldown (SMS-bomb vector) and leaks full phone number in the response | F11: P1 | G11: SaaS Readiness Review | H11: server.py:1372,1386,1396,1397 | I11: S | J11: Done | L11: 2026-08-11 | M11: 2026-08-11 | N11: Yes | O11: Shipped in FIX-006-A (c57b550).
A12: S1-01 | B12: Sprint 1 | C12: Scale/Ops | D12: Externalize the follow-up scheduler | E12: In-process 300s loop triple-fires (duplicate emails/alerts) with 3 replicas, dies with 1. Move to a single external cron/worker or add leader election. | F12: P0 | G12: Schema/Scale/Go-Live Review | H12: server.py:2765, 4946 | I12: M | J12: Done | L12: 2026-08-09 | M12: 2026-08-09 | N12: Yes | O12: Shipped in FIX-002-D ((this commit)).
A13: S1-02 | B13: Sprint 1 | C13: Scale/Ops | D13: Index phone, drop Python-side filter | E13: OTP login + WhatsApp routing do a full collection scan with no phone index, capped at 2000-5000 docs (silent lockout beyond that). Add (tenant_id, phone) index. | F13: P0 | G13: Schema/Scale/Go-Live Review | H13: server.py:1357,1419,4004 | I13: S | J13: Done | L13: 2026-08-09 | M13: 2026-08-09 | N13: Yes | O13: Shipped in FIX-002-A (e21a9b3).
A14: S1-03 | B14: Sprint 1 | C14: Scale/Ops | D14: Move all uploads to obj_store | E14: Voice notes, meetings, ledger uploads write to local disk — lost on restart, invisible across replicas. Route everything through the existing obj_store path; delete the local /api/files path. | F14: P0 | G14: Schema/Scale/Go-Live Review | H14: server.py:1739,1902,3032; ledger.py:146 | I14: M | J14: Done | L14: 2026-08-09 | M14: 2026-08-09 | N14: Yes | O14: Shipped in FIX-002-E ((this commit)).
A15: S1-04 | B15: Sprint 1 | C15: Scale/Ops | D15: Commit real deployment config | E15: No Dockerfile/Procfile exists. Pin worker count, add graceful shutdown for in-flight LLM calls, request-size caps. | F15: P0 | G15: Schema/Scale/Go-Live Review | H15: (missing — new file) | I15: M | J15: Done | L15: 2026-08-09 | M15: 2026-08-09 | N15: Yes
A16: S1-05 | B16: Sprint 1 | C16: Scale/Ops | D16: Timeout + concurrency-limit LLM calls | E16: No asyncio.wait_for on LLM calls; one shared key across all tenants means a burst of voice-capture cascades 429s with no ceiling. Add timeout + semaphore. | F16: P1 | G16: Schema/Scale/Go-Live Review | H16: core.py:177 | I16: M | J16: Done | L16: 2026-08-09 | M16: 2026-08-09 | N16: Yes | O16: Shipped in FIX-002-B (6b6fc25).
A17: S1-06 | B17: Sprint 1 | C17: Scale/Ops | D17: Fix hardcoded purchase_payment key | E17: Owner-approval loop, pending-purchases dashboard, and payment-overdue alerts only recognize the textile pipeline key. Non-textile tenants silently lose their sign-off + payment tracking. | F17: P0 | G17: Schema/Scale/Go-Live Review | H17: routers/decisions.py:166; server.py:2429; routers/brief.py:95,98,238,262 | I17: M | J17: Done | L17: 2026-08-04 | M17: 2026-08-04 | N17: Yes | O17: Shipped in FIX-001-A (cb84474+69f4ce3).
A18: S2-01 | B18: Sprint 2 | C18: Tenancy/Data | D18: Add _ensure_owned() helper | E18: Many update_one/delete_* calls filter by {'id': X} only after an earlier tenant-scoped read. UUID makes it safe today but drift/leak risk. Centralize the pattern. | F18: P1 | G18: SaaS Readiness Review | H18: routers/tasks.py:317,360,395; decisions.py:144-227; brain_docs.py:320,329; ledger.py:585,638,684 | I18: M | J18: Done | L18: 2026-08-09 | M18: 2026-08-09 | N18: No | O18: Shipped in FIX-001-C (da29cfd).
A19: S2-02 | B19: Sprint 2 | C19: Tenancy/Data | D19: Complete TENANT_COLLECTIONS wipe | E19: Tenant deletion omits brain_context, brain_documents, capture_drafts, platform_alerts, reclassify_jobs, signup_sessions, and never deletes uploaded files. GDPR gap. | F19: P1 | G19: SaaS Readiness Review | H19: routers/admin.py:161-186 | I19: S | J19: Done | L19: 2026-08-04 | M19: 2026-08-04 | N19: No | O19: Shipped in FIX-001-E (65cea2c).
A20: S2-03 | B20: Sprint 2 | C20: Tenancy/Data | D20: Tenant-scope OTP + WhatsApp phone routing | E20: Two users in different tenants sharing a phone can log into the wrong workspace, or hijack another tenant's inbound WhatsApp. | F20: P0 | G20: Schema/Scale/Go-Live Review | H20: server.py:1418-1428,1357; 3999-4028 | I20: M | J20: Done | L20: 2026-08-09 | M20: 2026-08-09 | N20: Yes | O20: Shipped in FIX-003-A (6a1ecec).
A21: S2-04 | B21: Sprint 2 | C21: Tenancy/Data | D21: Fix cross-tenant WhatsApp log leak | E21: whatsapp/logs OR-includes tenant_id:None rows, visible to every tenant owner. | F21: P1 | G21: SaaS Readiness Review | H21: server.py:3993-3995 | I21: S | J21: Done | L21: 2026-08-09 | M21: 2026-08-09 | N21: No | O21: Shipped in FIX-003-A (6a1ecec).
A22: S2-05 | B22: Sprint 2 | C22: Tenancy/Data | D22: Fix unfiltered enrich_decisions fetch | E22: Related tasks/users fetched with no tenant filter; safe only because task_ids can't currently contain a foreign UUID. | F22: P2 | G22: SaaS Readiness Review | H22: server.py:2142-2158; routers/decisions.py:44,172-175 | I22: S | J22: Done | L22: 2026-08-10 | M22: 2026-08-10 | N22: No | O22: Shipped in FIX-003-B (f18bbc3).
A23: S2-06 | B23: Sprint 2 | C23: Tenancy/Data | D23: Add session invalidation on logout/password-change | E23: JWT stays valid 7 days after logout; no jti/token-version, so a stolen session can't be revoked. | F23: P1 | G23: SaaS Readiness Review | H23: core.py:225-226 | I23: M | J23: Done | L23: 2026-08-10 | M23: 2026-08-10 | N23: No | O23: Shipped in FIX-003-C (f48bd24).
A24: S2-07 | B24: Sprint 2 | C24: Tenancy/Data | D24: Add email verification + password reset | E24: No self-serve recovery flow exists anywhere; enterprise-deal blocker. | F24: P1 | G24: SaaS Readiness Review | H24: routers/auth.py | I24: M | J24: Done | L24: 2026-08-10 | M24: 2026-08-10 | N24: No | O24: Shipped in FIX-003-D (4ef865e).
A25: S2-08 | B25: Sprint 2 | C25: Tenancy/Data | D25: Fix dead contacts.kind index | E25: Index uses 'kind', every read/write uses 'type'. Index (tenant_id, type) instead. | F25: P1 | G25: Schema/Scale/Go-Live Review | H25: server.py:4865 | I25: S | J25: Done | L25: 2026-08-10 | M25: 2026-08-10 | N25: No | O25: Shipped in FIX-003-B (f18bbc3).
A26: S2-09 | B26: Sprint 2 | C26: Tenancy/Data | D26: Fix denormalized-name staleness | E26: assignee_role / contact_name copies go stale on rename and are shown to users. Add refresh-on-rename. | F26: P2 | G26: Schema/Scale/Go-Live Review | H26: routers/tasks.py; server.py:3326 | I26: S | J26: Done | L26: 2026-08-10 | M26: 2026-08-10 | N26: No | O26: Shipped in FIX-003-C (f48bd24).
A27: S2-10 | B27: Sprint 2 | C27: Tenancy/Data | D27: Handle concurrent-registration race | E27: Same-email concurrent registers can race past the pre-check and hit the unique index, throwing a raw 500 instead of a clean 400. | F27: P2 | G27: Schema/Scale/Go-Live Review | H27: routers/auth.py:92-93 | I27: S | J27: Done | L27: 2026-08-10 | M27: 2026-08-10 | N27: No | O27: Shipped in FIX-003-B (f18bbc3).
... A29: S2-12 | B29: Sprint 2 | C29: Tenancy/Data | D29: Fix 'active workflows' hardcoded terminal stages | E29: KPI checks stage NOT IN [delivered, paid] — non-textile terminal stages never match, so the count only ever climbs. | F29: P2 | G29: Schema/Scale/Go-Live Review | H29: server.py:2433 | I29: S | J29: Done | L29: 2026-08-10 | M29: 2026-08-10 | N29: No | O29: Already closed by FIX-001-F; regression-guarded in FIX-003-B.
A30: S3-01 | B30: Sprint 3 | C30: Billing/AI-Keys | D30: Integrate real billing (Stripe or Razorpay) | E30: stripe is in requirements.txt but never imported. No subscription billing exists at all today. | F30: P0 | G30: SaaS Readiness Review | H30: requirements.txt:129 | I30: L | J30: Backlog | N30: Yes
A31: S3-02 | B31: Sprint 3 | C31: Billing/AI-Keys | D31: Add plan / entitlement fields to tenant doc | E31: No plan, trial_ends_at, seat_limit, or feature_flags — every tenant is on unlimited free forever. | F31: P1 | G31: SaaS Readiness Review | H31: tenant document schema | I31: M | J31: Done | L31: 2026-08-10 | M31: 2026-08-10 | N31: Yes | O31: Shipped in FIX-005-A (afbf9b8).
A32: S3-03 | B32: Sprint 3 | C32: Billing/AI-Keys | D32: Per-tenant AI key resolver | E32: All AI keys are one global pool shared by every tenant; one rate-limited/leaked key breaks 100% of tenants. Add per-tenant key columns + fallback resolver. | F32: P0 | G32: SaaS Readiness Review | H32: config.py:53-60; core.py:177-205; routers/admin.py:335-348 | I32: L | J32: Done | L32: 2026-08-10 | M32: 2026-08-10 | N32: Yes | O32: Shipped in FIX-005-A (afbf9b8).
A33: S3-04 | B33: Sprint 3 | C33: Billing/AI-Keys | D33: Enforce usage quotas (402 on exceed) | E33: Usage telemetry is estimation-only; no hard limit stops a tenant from running up unlimited LLM cost. | F33: P1 | G33: SaaS Readiness Review | H33: services/usage.py | I33: M | J33: Done | L33: 2026-08-10 | M33: 2026-08-10 | N33: Yes | O33: Shipped in FIX-005-B (29d2238).
A34: S4-01 | B34: Sprint 4 | C34: AI/Brain | D34: Fix text-index stemming + index db.memory | E34: default_language='none' disables stemming (refund != refunds); db.memory has no text index at all, only regex scan. | F34: P2 | G34: AI/Brain/Agentic Review | H34: server.py:4894; brain.py:250-255 | I34: S | J34: Backlog | N34: No
A35: S4-02 | B35: Sprint 4 | C35: AI/Brain | D35: Fix task-done Brain write-coverage gap + link provenance | E35: Execution-plan-complete path skips record_context; add decision_id linkage so decision->task->outcome is reconstructable. | F35: P1 | G35: AI/Brain/Agentic Review | H35: tasks.py:507; services/brain_context.py | I35: M | J35: Backlog | N35: No
A36: S4-03 | B36: Sprint 4 | C36: AI/Brain | D36: Rename brain_contexts -> brain_query_cache | E36: Kills the dangerous brain_context / brain_contexts name collision. | F36: P2 | G36: AI/Brain/Agentic Review | H36: brain.py:714,752,794 | I36: S | J36: Backlog | N36: No
A37: S4-04 | B37: Sprint 4 | C37: AI/Brain | D37: Unify /ask and /brain/agent retrieval reach | E37: /ask never reads brain_context or brain_documents — provenance answers only work on the Dex agent path. Give both the same reach. | F37: P1 | G37: AI/Brain/Agentic Review | H37: routers/brain.py:52,205 | I37: M | J37: Backlog | N37: No
A38: S4-05 | B38: Sprint 4 | C38: AI/Brain | D38: Extract + chunk + embed documents at ingest | E38: Uploaded documents are stored as metadata only; body text is never read at ingest. Add server-side extraction + chunking + embeddings into a new brain_chunks collection. | F38: P1 | G38: AI/Brain/Agentic Review | H38: routers/brain_docs.py:147-213 | I38: L | J38: Backlog | N38: No
A39: S4-06 | B39: Sprint 4 | C39: AI/Brain | D39: Adopt vector search + hybrid retrieval | E39: Move from keyword-only BM25/regex to embeddings (Atlas Vector Search if on Atlas, else Qdrant/pgvector) fused with existing text search. | F39: P1 | G39: AI/Brain/Agentic Review | H39: (new infra) | I39: L | J39: Backlog | N39: No
A40: S4-07 | B40: Sprint 4 | C40: AI/Brain | D40: Formalize a tool registry | E40: The 10 _compute_* + 4 _tool_* handlers already have a clean typed contract — wrap in Pydantic in/out models and register centrally. | F40: P2 | G40: AI/Brain/Agentic Review | H40: routers/brain.py; routers/brain_router.py | I40: M | J40: Backlog | N40: No
A41: S4-08 | B41: Sprint 4 | C41: AI/Brain | D41: Add bounded planner-executor loop + native function-calling | E41: /brain/agent is single-turn (plan -> fan-out -> synthesize, no re-plan). Add an observe-then-replan loop and migrate to Anthropic tools=[...]. | F41: P2 | G41: AI/Brain/Agentic Review | H41: routers/brain_router.py:266-277,481-482 | I41: L | J41: Backlog | N41: No
A42: S4-09 | B42: Sprint 4 | C42: AI/Brain | D42: Add per-conversation agent memory | E42: Every LLM call gets a fresh random session_id; planner and synthesizer don't even share context. | F42: P2 | G42: AI/Brain/Agentic Review | H42: routers/brain_router.py:95,353 | I42: M | J42: Backlog | N42: No
A43: S4-10 | B43: Sprint 4 | C43: AI/Brain | D43: Expand Brain write coverage to finance/workflow/meetings | E43: Only 6 write sites exist today; all payments/invoices/workflow-advance/meetings/ingestion events are invisible to the Brain. | F43: P2 | G43: AI/Brain/Agentic Review | H43: ledger.py:521-838; server.py (workflow advance, meetings) | I43: L | J43: Backlog | N43: No
A44: S4-11 | B44: Sprint 4 | C44: AI/Brain | D44: Make tag vocabulary tenant/industry-configurable | E44: _TAG_VOCAB is 10 hardcoded manufacturing buckets; clinics/restaurants/agencies get silently under-tagged, hurting retrieval recall. | F44: P2 | G44: AI/Brain/Agentic Review | H44: services/brain_context.py:36-47 | I44: M | J44: Backlog | N44: No
A45: S5-01 | B45: Sprint 5 | C45: DevOps/Migration | D45: Stand up a staging environment | E45: Mirror production config/data shape so every fix above is verified before it touches real tenants. | F45: P0 | G45: Go-Live Gate | H45: (infra) | I45: M | J45: Backlog | N45: Yes
... A54: S5-10 | B54: Sprint 5 | C54: DevOps/Migration | D54: Final go/no-go review | E54: Walk the Go-Live Checklist tab end to end with the team before opening self-serve signup or onboarding client #1. | F54: P0 | G54: Go-Live Gate | H54: (process) | I54: S | J54: Backlog | N54: Yes
A55: RBAC-01 | B55: Sprint 2.5 | C55: Endpoint gate | D55: Auth-gate onboarding drafts | E55: GET/PATCH /onboarding/draft/{draft_id} become 'signed link only': add a signed HMAC on the draft URL (draft_id + issued_at + signature). Only the client that created the draft can read/write. Add rate-limit per IP. Accept: cannot access another draft even with a leaked UUID. | F55: P0 | G55: RBAC & People Audit | H55: (various) | I55: S | J55: Done | L55: 2026-08-10 | M55: 2026-08-10 | N55: Yes | O55: Shipped in FIX-004-A (a44135f).
A56: RBAC-02 | B56: Sprint 2.5 | C56: Endpoint gate | D56: CAPTCHA + IP rate-limit on /register | E56: Turnstile (Cloudflare, free) or hCaptcha on POST /register. IP rate limit: 3 registrations/hour/IP. Accept: bot creating 100 tenants gets blocked at #4. | F56: P0 | G56: RBAC & People Audit | H56: (various) | I56: M | J56: Done | L56: 2026-08-10 | M56: 2026-08-10 | N56: Yes | O56: Shipped in FIX-004-A (a44135f).
A57: RBAC-03 | B57: Sprint 2.5 | C57: Endpoint gate | D57: Auth-gate + rate-limit signup AI endpoints | E57: /website-intel, /signup/tts, /signup/stt need: CAPTCHA on first call per IP + per-IP 10-req/hour ceiling. SSRF guard on /website-intel (block private IP ranges, allowlist protocols). Accept: unauth attacker cannot burn > $0.10 of AI credit. | F57: P0 | G57: RBAC & People Audit | H57: (various) | I57: M | J57: Done | L57: 2026-08-10 | M57: 2026-08-10 | N57: Yes | O57: Shipped in FIX-004-A (a44135f).
A58: RBAC-04 | B58: Sprint 2.5 | C58: Endpoint gate | D58: Symmetric role gate on /workflows create+delete | E58: POST /workflows: add require_perm('workflows') at minimum, ideally require_perm('workflow_create') if we split it. Accept: employee without workflow perm gets 403 on create. | F58: P1 | G58: RBAC & People Audit | H58: (various) | I58: S | J58: Done | L58: 2026-08-10 | M58: 2026-08-10 | N58: No | O58: Shipped in FIX-004-C (9b3a1c3).
A59: RBAC-05 | B59: Sprint 2.5 | C59: Endpoint gate | D59: Gate /captures approve/reject/reassign | E59: Approving/rejecting a capture creates real records — must be require_perm('approvals') or role-gated. Accept: employee without approvals perm gets 403. | F59: P1 | G59: RBAC & People Audit | H59: (various) | I59: S | J59: Done | L59: 2026-08-10 | M59: 2026-08-10 | N59: No | O59: Shipped in FIX-004-C (9b3a1c3).
A60: RBAC-06 | B60: Sprint 2.5 | C60: Endpoint gate | D60: Gate /follow-up/run to owner or team_manage | E60: Manual follow-up trigger burns LLM. Restrict to owner or perm(team_manage). | F60: P1 | G60: RBAC & People Audit | H60: (various) | I60: S | J60: Done | L60: 2026-08-10 | M60: 2026-08-10 | N60: No | O60: Shipped in FIX-004-C (9b3a1c3).
A61: RBAC-07 | B61: Sprint 2.5 | C61: Endpoint gate | D61: Role gates across tasks router | E61: 17 endpoints in routers/tasks.py are auth-only. Group: reassign + priority-change + delete-execution-plan need perm('team_manage'); prioritize (LLM) needs perm('tasks'). Add explicit decorators. Accept: cross-role matrix test passes. | F61: P1 | G61: RBAC & People Audit | H61: (various) | I61: M | J61: Done | L61: 2026-08-10 | M61: 2026-08-10 | N61: No | O61: Shipped in FIX-004-C (9b3a1c3).
A62: RBAC-08 | B62: Sprint 2.5 | C62: Endpoint gate | D62: Gate voice/meeting AI on perm(voice_capture) | E62: voice_capture permission exists in PERMISSION_KEYS but only used by 3 endpoints. Add to /voice-notes text+audio and /meetings audio. Accept: perm-less employee can't burn STT credits. | F62: P1 | G62: RBAC & People Audit | H62: (various) | I62: S | J62: Done | L62: 2026-08-10 | M62: 2026-08-10 | N62: No | O62: Shipped in FIX-004-C (9b3a1c3).
A63: RBAC-09 | B63: Sprint 2.5 | C63: Endpoint gate | D63: Add decorator gate to leaves approve/reject | E63: Move inline _can_approve_leave into require_perm('leave_approve'). Keep inline check as defense-in-depth. Accept: reviewer reading the route sees the gate in the signature. | F63: P1 | G63: RBAC & People Audit | H63: (various) | I63: S | J63: Done | L63: 2026-08-10 | M63: 2026-08-10 | N63: No | O63: Shipped in FIX-004-C (9b3a1c3).
A64: RBAC-10 | B64: Sprint 2.5 | C64: Endpoint gate | D64: Split brain export permission | E64: POST /brain/export requires perm('brain_export') (new key) instead of perm('ask'). Accept: user with 'ask' but not 'brain_export' gets 403. | F64: P2 | G64: RBAC & People Audit | H64: (various) | I64: S | J64: Done | L64: 2026-08-10 | M64: 2026-08-10 | N64: No | O64: Shipped in FIX-004-C (9b3a1c3).
A65: RBAC-11 | B65: Sprint 2.5 | C65: Endpoint gate | D65: Gate memory write on perm(brain) | E65: POST /memory is auth-only. Restrict to perm('brain'). Accept: memory list still readable by all, write gated. | F65: P2 | G65: RBAC & People Audit | H65: (various) | I65: S | J65: Done | L65: 2026-08-10 | M65: 2026-08-10 | N65: No | O65: Shipped in FIX-004-C (9b3a1c3).
A66: RBAC-12 | B66: Sprint 2.5 | C66: Data model | D66: Email-per-tenant uniqueness (kill global unique) | E66: Move email uniqueness from `users.email` global unique to compound `(tenant_id, email)`. Register + login flow accept optional tenant hint the same way FIX-003-A did for phones (single-tenant fast path + ambiguity picker for multi-tenant email). Migration ledger entry. Accept: same email registered in 2 workspaces works; login prompts workspace picker. | F66: P0 | G66: RBAC & People Audit | H66: (various) | I66: L | J66: Done | L66: 2026-08-10 | M66: 2026-08-10 | N66: Yes | O66: Shipped in FIX-004-B (56399d6). Depends on RBAC-13
... A71: RBAC-17 | B71: Sprint 2.5 | C71: Data model | D71: 'Pending invite' status on user | E71: Add user.invite_status = 'pending' | 'accepted'. Set 'pending' on create-with-invite; flip to 'accepted' on first OTP verify. GET /users returns the flag; admin UI shows a 'Pending' badge. Add resend-invite + revoke-invite endpoints. Accept: invited user shows Pending; revoked user cannot verify. | F71: P1 | G71: RBAC & People Audit | H71: (various) | I71: S | J71: Done | L71: 2026-08-10 | M71: 2026-08-10 | N71: No | O71: Shipped in FIX-004-E (1541439).
A72: RBAC-18 | B72: Sprint 4 | C72: Data model | D72: Department/branch scope on permissions | E72: Add `branches` collection + membership.branch_id + permission modifier '[perm]:branch_X'. Blocks multi-location SMEs. Accept: Finance Manager in Store A sees zero Store B invoices. | F72: P2 | G72: RBAC & People Audit | H72: (various) | I72: L | J72: Backlog | N72: No | O72: Depends on RBAC-13
A73: RBAC-19 | B73: Sprint 4 | C73: Data model | D73: User groups | E73: New `user_groups` collection: {tenant_id, name, member_ids, permissions[]}. user_perms merges (role) + (user override) + (union of groups). Accept: adding 'inventory' perm to 'Regional Managers' group instantly grants it to all group members. | F73: P2 | G73: RBAC & People Audit | H73: (various) | I73: M | J73: Backlog | N73: No | O73: Depends on RBAC-13
A74: RBAC-20 | B74: Sprint 2.5 | C74: Compliance | D74: Immutable audit log (audit_log collection) | E74: New collection audit_log with append-only writes: {actor_id, actor_email, actor_ip, actor_ua, action, entity_type, entity_id, before, after, timestamp, tenant_id}. Wrap every mutating endpoint with a middleware or decorator. Read-only endpoint /admin/audit-log. Accept: deleting a decision leaves an audit row; audit rows cannot be updated/deleted via API. | F74: P0 | G74: RBAC & People Audit | H74: (various) | I74: M | J74: Done | L74: 2026-08-10 | M74: 2026-08-10 | N74: Yes | O74: Shipped in FIX-004-F (cc7c698).
A75: RBAC-21 | B75: Sprint 2.5 | C75: UX + security | D75: /me/sessions endpoint + revoke by device | E75: Track session metadata on jti (device UA, IP, last-seen). Add GET /me/sessions returning active sessions; DELETE /me/sessions/{jti} revokes one; DELETE /me/sessions revokes ALL except current. Uses FIX-003-C session_revocation infra. Accept: user can see + revoke individual devices. | F75: P0 | G75: RBAC & People Audit | H75: (various) | I75: M | J75: Done | L75: 2026-08-10 | M75: 2026-08-10 | N75: Yes | O75: Shipped in FIX-004-G (d95ae44).
A76: RBAC-22 | B76: Sprint 2.5 | C76: UX + security | D76: Off-boarding workflow (deprovisioning wizard) | E76: POST /users/{id}/deprovision runs: revoke all sessions, reassign owned tasks to specified user, transfer in-flight decisions, mark authored contacts as reassigned, invalidate all invite tokens. Idempotent. Owner-only. Accept: after deprovision the departing user has zero owned entities. | F76: P0 | G76: RBAC & People Audit | H76: (various) | I76: L | J76: Done | L76: 2026-08-10 | M76: 2026-08-10 | N76: Yes | O76: Shipped in FIX-004-H (309ef84). Depends on RBAC-21
A77: RBAC-23 | B77: Sprint 3 | C77: Security | D77: TOTP-based 2FA | E77: Standard pyotp-based flow: enroll (QR + secret), verify, backup codes. Second-factor on login when enabled. Recovery via email + backup code. Accept: user with 2FA enabled cannot log in with password alone. | F77: P1 | G77: RBAC & People Audit | H77: (various) | I77: M | J77: Done | L77: 2026-08-10 | M77: 2026-08-10 | N77: No | O77: Shipped in FIX-005-D (a8da19b).
A78: RBAC-24 | B78: Sprint 3 | C78: UX | D78: Ownership transfer flow | E78: POST /tenant/transfer-ownership {new_owner_user_id}: promote target to owner, demote current to specified role, cascade billing rebind. Requires 2FA confirm from current owner. Accept: last owner promoted successfully, previous owner remains as employee. | F78: P1 | G78: RBAC & People Audit | H78: (various) | I78: M | J78: Done | L78: 2026-08-10 | M78: 2026-08-10 | N78: No | O78: Shipped in FIX-005-D (a8da19b). Depends on RBAC-13
A79: RBAC-25 | B79: Sprint 3 | C79: Compliance | D79: Consent tracking for AI features (DPDP) | E79: tenant.ai_consent = {granted_at, granted_by_user_id, ip, ua, version}. Show a first-run modal 'DecisionOS uses AI (Anthropic) to process operational data. Consent required.' Gate all AI endpoints on tenant.ai_consent. Log revocations. Accept: fresh tenant cannot use /ask until consent granted. | F79: P1 | G79: RBAC & People Audit | H79: (various) | I79: M | J79: Done | L79: 2026-08-10 | M79: 2026-08-10 | N79: No | O79: Shipped in FIX-005-C (4115624).
A80: RBAC-26 | B80: Sprint 4 | C80: UX | D80: Approval delegation ('acting-as') | E80: user.acting_as: {delegate_user_id, from, to}. When present, approvals routed to `delegate_user_id`. Combines with leaves. Accept: on-leave approver's tasks auto-route to their delegate; badge shows 'Acting for X'. | F80: P2 | G80: RBAC & People Audit | H80: (various) | I80: M | J80: Backlog | N80: No
A81: RBAC-27 | B81: Sprint 4 | C81: UX | D81: Time-bounded elevated permissions | E81: membership.temp_grants[] = [{perm, granted_by, expires_at, reason}]. Bootstrap TTL sweep to auto-revoke. Audit log entry on grant + revoke. Accept: contractor gets 'finance' perm for 30 days, auto-revoked. | F81: P2 | G81: RBAC & People Audit | H81: (various) | I81: M | J81: Backlog | N81: No | O81: Depends on RBAC-13
A82: RBAC-28 | B82: Sprint 4 | C82: Auth | D82: SSO (Google + Microsoft OAuth) | E82: Add /auth/oauth/{provider}/start + callback. Map OAuth email to user via membership lookup. Handle first-time users (auto-provision if tenant allows). Accept: user with matching email can sign in with Google. | F82: P2 | G82: RBAC & People Audit | H82: (various) | I82: L | J82: Backlog | N82: No | O82: Depends on RBAC-12
A83: RBAC-29 | B83: Sprint 4 | C83: Programmatic | D83: Per-user API keys | E83: New api_keys collection: {user_id, tenant_id, name, prefix, hash, scopes, created_at, last_used_at}. UI to create/revoke. Bearer-token auth reads api_key instead of JWT. Rate limits per key. Accept: script hits /tasks with key, works, revoke kills it. | F83: P2 | G83: RBAC & People Audit | H83: (various) | I83: M | J83: Backlog | N83: No
A84: RBAC-30 | B84: Sprint 5 | C84: UX | D84: Client/customer read-only portal | E84: Share a workflow (procurement order, complaint) with an external email via a signed link. Recipient sees status timeline + can add comments, no login. Accept: customer email link opens read-only page; commenting works without account. | F84: P2 | G84: RBAC & People Audit | H84: (various) | I84: L | J84: Backlog | N84: No

Sheet Fix Log
A1: Fix Log — every change we make, in order
A2: Running record. Updated side-by-side after every shipped commit. Currently: 11 Done, 13 in backlog.
A4: Modules
A5: Module | B5: Name | C5: What it delivers | D5: Priority | E5: Status
A6: Module 1 | B6: Multi-tenant / Dynamic Workflows | C6: DONE. 6 fixes shipped: dynamic per-tenant workflow approval, workflow<->Finance link, tenant-scoped safety helpers, onboarding drafts + AI status tracking, complete tenant deletion (DPDP/GDPR), dynamic terminal stages. Non-textile tenants get their full lifecycle end-to-end. | D6: P0 for selling to any small business that isn't a textile manufacturer. | E6: 6/6 shipped.
A7: Module 2 | B7: Sprint 1 — Scale & Ops | C7: DONE. 6 fixes shipped: phone index (kills full-collection scans), LLM timeouts + concurrency semaphore, migration ledger, distributed leader lock (multi-replica-safe scheduler), obj_store for all uploads, and Dockerfile + Procfile with production-grade signal handling + healthcheck. | D7: Turns 'runs in Sharma demo' into 'survives 100 tenants under real load.' | E7: 6/6 shipped. Sprint 1 COMPLETE.
A8: Module 3 | B8: Sprint 2 – Tenancy & Data | C8: DONE. 12/12 shipped: tenant helpers (FIX-001-C), TENANT_COLLECTIONS wipe (FIX-001-E), OTP+WhatsApp tenant scoping (FIX-003-A), hygiene batch (FIX-003-B), JWT revocation + contact rename + AI regen status (FIX-003-C), email verification + password reset (FIX-003-D). | D8: P0 tenancy bugs closed. Remaining are hardening (session invalidation, email verification, dead index cleanup, denormalized-name staleness) — not blockers for a controlled beta but recommended before wider rollout. | E8: 12/12 shipped. Sprint 2 COMPLETE.
A9: Fix Log entries
A10: Fix ID | B10: Module | C10: Backlog ID | D10: Title | E10: Description | F10: Files touched | G10: Related tests | H10: Status | I10: Priority | J10: Started | K10: Finished | L10: PR / Commit | M10: Notes / gotchas
A11: FIX-001-A | B11: Multi-tenant / Dynamic Workflows | C11: S1-06 | D11: Kill purchase_payment textile hardcode | E11: Owner-approval loop + dashboard + payment-overdue alerts filtered on the literal 'purchase_payment' string — silently broke for non-textile tenants. Fix uses per-tenant pipeline lookup. | F11: routers/decisions.py:166; server.py:2429; routers/brief.py:95,98,238,262 | G11: tests/test_workflows_dynamic.py — 19 tests | H11: Done | I11: P0 | J11: 2026-08-04 | K11: 2026-08-04 | L11: cb84474 + 69f4ce3 | M11: First unblock for selling to any small business that isn't a manufacturer.
A12: FIX-001-B | B12: Multi-tenant / Dynamic Workflows | C12: (discovered mid-fix) | D12: Wire workflow -> Finance auto-expense on procurement completion | E12: Workflow terminal-stage advance auto-creates a pending-bill expense in Finance linked to the workflow. Notifies finance role. Idempotent, fire-and-forget. | F12: server.py:2236; routers/ledger.py:222 | G12: tests/test_workflow_finance_link.py — 17 tests | H12: Done | I12: P1 | J12: 2026-08-04 | K12: 2026-08-09 | L12: 98d0291 | M12: Founder no longer records purchases twice. Bill upload -> OCR promotion flow is a follow-up.
A13: FIX-001-C | B13: Multi-tenant / Data Integrity | C13: S2-01 | D13: Add tenant-scoped safety helpers (_ensure_owned) | E13: Every update_one/delete_* now routed through services/tenancy.py::tenant_filter() which pins BOTH id AND tenant_id. Python TypeError blocks smuggling different tenant_id via extras. | F13: services/tenancy.py (new); ~25 sites across routers + server.py | G13: tests/test_tenancy_helpers.py — 16 tests | H13: Done | I13: P1 | J13: 2026-08-04 | K13: 2026-08-09 | L13: da29cfd | M13: Grep found 25+ sites vs. audit's 13. Discipline lesson: always grep AFTER refactor.
A14: FIX-001-D | B14: Multi-tenant / Onboarding | C14: S1-04 partial + new | D14: Onboarding drafts + AI status tracking + retry endpoint | E14: Two gaps closed: silent AI degradation (ai_setup_status per generator + regenerate endpoint) and data loss on failure (onboarding_drafts persist each wizard step). | F14: services/ai_setup.py + services/onboarding_drafts.py (new); +5 endpoints | G14: tests/test_onboarding_flow.py — 27 tests | H14: Done | I14: P1 | J14: 2026-08-09 | K14: 2026-08-09 | L14: 3bc0059 | M14: Idempotent-register (Comprehensive-scope 3e) and onboarding_drafts TTL deferred.
A15: FIX-001-E | B15: Multi-tenant / Data Integrity | C15: S2-02 | D15: Complete TENANT_COLLECTIONS wipe + file deletion (DPDP/GDPR) | E15: TENANT_COLLECTIONS grown to 30 (was missing brain_context + brain_documents). Now also iterates db.files and deletes each object from storage before wiping. | F15: routers/admin.py; services/obj_store.py::delete_object (new) | G15: tests/test_tenant_deletion.py — 8 tests (incl. drift-detection) | H15: Done | I15: P1 | J15: 2026-08-04 | K15: 2026-08-04 | L15: 65cea2c | M15: Legacy local-disk files depend on Sprint 1 S1-03 to move all uploads to obj_store.
A16: FIX-001-F | B16: Multi-tenant / Dynamic Workflows | C16: WF-3 | D16: Dynamic pipeline terminal stages ('active workflows' stops climbing forever) | E16: 4 places hardcoded ['delivered','paid'] as terminal stages. New services/workflows.py::all_terminal_stages(om) + legacy hedge. All 4 sites now use dynamic exclusion. | F16: services/workflows.py; server.py:2500, :3697, :3745, :3911 | G16: tests/test_workflows_dynamic.py — 12 additional tests | H16: Done | I16: P2 | J16: 2026-08-09 | K16: 2026-08-09 | L16: 8235c61 | M16: Calendar deliveries also hardcodes pipeline TYPES - see FIX-FUP-09.
A17: FIX-002-A | B17: Sprint 1 / Scale & Ops | C17: S1-02 | D17: Phone index + kill full-collection scans on OTP + WhatsApp routing | E17: 3 hot paths (OTP request, OTP verify, resolve_wa_tenant) ran full-collection scans over db.users on every call, capped at 2000/5000 users (silent lockout beyond). Fix indexes new phone_norm field; hot paths become exact-match lookups. Bootstrap includes idempotent backfill for existing users. | F17: services/phone.py (new); server.py bootstrap + 3 hot paths; routers/auth.py; routers/team.py | G17: tests/test_phone_indexed_lookup.py — 16 tests (parity, query shape, no-cap guard) | H17: Done | I17: P0 | J17: 2026-08-09 | K17: 2026-08-09 | L17: e21a9b3 | M17: Existing OTP hashes still verify (parity-tested). server.py:4623 (per-tenant scan) noted but out of scope.
A18: FIX-002-B | B18: Sprint 1 / Scale & Ops | C18: S1-05 | D18: LLM call timeouts + concurrency semaphore | E18: One shared Anthropic key + no timeout + no concurrency cap = 50 concurrent voice captures cascade into 429s and unbounded latency. New services/llm_limits.py::guarded_llm wraps every LLM call with asyncio.wait_for + shared semaphore. Covers _ResilientChat + 4 direct LlmChat sites. | F18: services/llm_limits.py (new); core.py::_ResilientChat; server.py (2 Gemini); routers/admin.py; routers/ledger.py | G18: tests/test_llm_limits.py — 14 tests (peak-concurrency, timeout-releases-slot, exception-releases-slot) | H18: Done | I18: P1 | J18: 2026-08-09 | K18: 2026-08-09 | L18: 6b6fc25 | M18: Per-process only. Cross-process rate limiting needs Redis (Sprint 3 with per-tenant keys). STT paths (Whisper/Sarvam) NOT wrapped - separate follow-up.
A19: FIX-002-C | B19: Sprint 1 / Scale & Ops | C19: (new: raised during Q&A) | D19: Migration ledger for MongoDB schema changes | E19: Ad-hoc bootstrap migrations are fine for additive changes (new fields, new indexes, safe backfills) but unsafe the moment we ship a destructive migration (rename+copy+delete, data reshape). Add db.migrations_applied collection + a migrate(name, fn) helper so migrations run exactly once and non-idempotent changes are safe. | F19: services/migrations.py (new); server.py bootstrap block | G19: tests/test_migrations.py — helper contract + idempotency | H19: Done | I19: P1 | J19: 2026-08-09 | K19: 2026-08-09 | L19: (this commit) | M19: Prerequisite for S1-03 (uploads migration). MongoDB doesn't need Alembic (no DDL) but does need this ledger discipline.
A20: FIX-002-D | B20: Sprint 1 / Scale & Ops | C20: S1-01 | D20: Externalize the follow-up scheduler (multi-replica safe) | E20: In-process 300s loop triple-fires with 3 replicas (duplicate emails/alerts), dies with 1. Options: (a) external cron + endpoint (b) in-process with distributed leader election. Design decision needed. | F20: server.py:2765 (scheduler loop); new endpoint or external cron config | G20: tests: single-fire under multiple simulated replicas | H20: Done | I20: P0 | J20: 2026-08-09 | K20: 2026-08-09 | L20: (this commit) | M20: Half-day fix. Requires design decision on external cron vs leader election.
A21: FIX-002-E | B21: Sprint 1 / Scale & Ops | C21: S1-03 | D21: Migrate all uploads to obj_store (kill local-disk file storage) | E21: Voice notes, meetings, ledger uploads write to local UPLOAD_DIR — lost on restart, invisible across replicas. Route everything through obj_store with tenant-prefixed paths; delete local /api/files path. Includes migration for existing local-disk records. | F21: server.py:1739,1902,3032; ledger.py:146; obj_store integration in all 3 paths | G21: tests: upload, download, cross-replica visibility, deletion | H21: Done | I21: P0 | J21: 2026-08-09 | K21: 2026-08-09 | L21: (this commit) | M21: Half-day. Depends on FIX-002-C for the migration. Also closes FIX-001-E EC8 (legacy local files for tenant deletion).
A22: FIX-002-F | B22: Sprint 1 / Scale & Ops | C22: S1-04 | D22: Commit real Dockerfile + Procfile with pinned worker count + graceful shutdown | E22: No Dockerfile exists (only .emergent/emergent.yml base-image pointer). Need a real deployable Dockerfile with worker count pinned, graceful shutdown for in-flight LLM work, request-size caps. | F22: backend/Dockerfile (new); backend/Procfile (new); backend/.dockerignore (new) | G22: tests/test_dockerfile.py - 25 static contract tests (multi-stage, non-root, healthcheck, secrets, apt cleanup, Procfile parity) | H22: Done | I22: P0 | J22: 2026-08-09 | K22: 2026-08-09 | L22: 5a4644e | M22: Multi-stage Python 3.12-slim build. Non-root user, HEALTHCHECK via Python stdlib on /api/health, tini as PID 1, --timeout-graceful-shutdown 60 (> 45s LLM cap from FIX-002-B). emergentintegrations installed from Emergent's CDN (regression guard: without extra-index-url, requirements install silently drops that package). Docker build not exercised in tests - daemon unavailable in this env; static tests cover structure + security. FIX-FUP-15 logged to wire docker build into CI. SPRINT 1 COMPLETE with this ship.
A23: FIX-FUP-01 | B23: Follow-up (from FIX-001-A) | C23: (logged during A) | D23: Delete WORKFLOW_OWNER_ROLE dead code | E23: server.py:212 defines WORKFLOW_OWNER_ROLE dict - nothing references it. | F23: server.py:212 | G23: test: import check + grep for zero refs | H23: Not Started | I23: P2 | M23: Dead code cleanup.
A24: FIX-FUP-02 | B24: Follow-up (from FIX-001-A) | C24: (logged during A) | D24: Clean 'purchase_payment' from AI onboarding prompt | E24: server.py:1094,1103 - operating-model AI prompt uses 'purchase_payment' as an example. Could bias AI toward textile key. | F24: server.py:1094, 1103 | G24: test: onboard non-textile tenant, assert no 'purchase_payment' in operating_model | H24: Not Started | I24: P2 | M24: Prevents textile leak from re-emerging via the prompt.
A25: FIX-FUP-03 | B25: Follow-up (from FIX-001-A) | C25: (logged during A) | D25: Memoize tenant_procurement_pipeline in brief.py | E25: Called TWICE per brief request (counter + drill-down). Minor inefficiency. | F25: routers/brief.py | G25: test: mock tenant_operating_model, assert called once | H25: Not Started | I25: P2 | M25: Small perf tidy.
A26: FIX-FUP-04 | B26: Follow-up (from FIX-001-B) | C26: (logged during B) | D26: Unique index on expenses.(tenant_id, workflow_id) | E26: Check + insert is not atomic. Rare race could double-create. Close with unique compound index. | F26: server.py bootstrap | G26: test: concurrent create_expense with same workflow_id | H26: Not Started | I26: P2 | M26: Belt-and-braces for FIX-001-B idempotency.
A27: FIX-FUP-05 | B27: Follow-up (from FIX-001-B) | C27: (logged during B) | D27: Bill upload -> OCR promotion flow (Finance side) | E27: Complete the story: Finance uploads bill, OCR extracts real amount, expense flips from awaiting_bill to reconciled. | F27: routers/ledger.py + existing OCR pipeline | G27: test: mock OCR + upload + status transition | H27: Not Started | I27: P1 | M27: One-click reconciliation finish for FIX-001-B.
A28: FIX-FUP-06 | B28: Follow-up (from FIX-001-C) | C28: (logged during C) | D28: 'id' footgun in tenant_filter | E28: Extras can overwrite id (though tenant scope still holds). Documented in tests; stricter version would reject. | F28: services/tenancy.py | G28: test already documents | H28: Not Started | I28: P2 | M28: Cosmetic hardening.
A29: FIX-FUP-07 | B29: Follow-up (from FIX-001-D) | C29: (logged during D) | D29: TTL index on onboarding_drafts | E29: Auto-expire ~30 days after last update. Bootstrap: create_index('updated_at', expireAfterSeconds=30*86400). | F29: server.py bootstrap | G29: test: verify index exists | H29: Not Started | I29: P2 | M29: Small bootstrap tweak.
A30: FIX-FUP-08 | B30: Follow-up (from FIX-001-D) | C30: (logged during D) | D30: Idempotent register by draft_id (Comprehensive-scope 3e) | E30: Network drop mid-register -> user retries -> 'Email already registered' 400. Fix: if draft completed with tenant_id, return existing session on retry. | F30: routers/auth.py::register | G30: test: register with draft_id twice, second returns existing tenant | H30: Not Started | I30: P1 | M30: Closes the last onboarding-flow paper cut.
A31: FIX-FUP-09 | B31: Follow-up (from FIX-001-F) | C31: (logged during F) | D31: tenant_sales_pipeline resolver (mirror of procurement) | E31: Calendar deliveries hardcodes pipeline TYPES ['distribution','sales_dispatch']. Add resolver like tenant_procurement_pipeline. | F31: services/workflows.py; calendar endpoint | G31: tests: bakery order_fulfilment shows in calendar deliveries | H31: Not Started | I31: P2 | M31: Extends FIX-001-A pattern to sales side.
A32: FIX-FUP-10 | B32: Follow-up (from FIX-002-A) | C32: (logged during 002-A) | D32: phone_norm on WhatsApp review UI + contact lookups | E32: server.py:4623 builds a phone_index for the WA review UI via Python-side normalization. Tenant-scoped (not a P0 like the global hot paths) but same pattern. | F32: server.py:4623 area | G32: test: query uses phone_norm | H32: Not Started | I32: P2 | M32: Consistency win, not a P0.
A33: FIX-FUP-11 | B33: Follow-up (from FIX-002-B) | C33: (logged during 002-B) | D33: Guard STT (Whisper/Sarvam) paths with llm_limits | E33: The FIX-002-B semaphore/timeout covers LlmChat paths. STT goes through OpenAISpeechToText and Sarvam wrappers separately - not yet guarded. | F33: server.py transcribe_audio_full and Sarvam wrapper | G33: test: mock STT, assert guarded_llm called | H33: Not Started | I33: P2 | M33: ~1 hour when someone hits an STT rate limit.
A34: FIX-FUP-12 | B34: Follow-up (from FIX-002-B) | C34: (logged during 002-B) | D34: Cross-process LLM rate limiting (Redis-backed) | E34: Semaphore is per-process. With multiple uvicorn workers, total in-flight = workers x cap. Ties to Sprint 3 (per-tenant AI keys) so per-tenant caps become meaningful. | F34: new services/llm_limits.py extension + Redis | G34: test: distributed semaphore behavior | H34: Not Started | I34: P1 | M34: Sprint 3 territory.
A35: FIX-FUP-13 | B35: Follow-up (from FIX-002-F) | C35: (logged during 002-F local run) | D35: Frontend install hardening: legacy-peer-deps | E35: npm install silently exited 0 with 0 packages because react-day-picker@8 peer-requires date-fns@^2||^3 but this project uses date-fns@4. Added frontend/.npmrc with legacy-peer-deps=true so every dev + CI `npm install` runs without needing --legacy-peer-deps flag. | F35: frontend/.npmrc (new) | G35: manual: npm install now completes (was silent 0-package exit) | H35: Done | I35: P0 | J35: 2026-08-09 | K35: 2026-08-09 | L35: 5a4644e | M35: The trap that blocked our first local frontend boot. Locked in as .npmrc so it doesn't happen again.
A36: FIX-FUP-14 | B36: Follow-up (from FIX-002-F) | C36: (logged during 002-F local run) | D36: Pin ajv@^8.20.0 across the tree (webpack crash fix) | E36: ajv-keywords@5 needs `ajv/dist/compile/codegen` (ajv v8), but a nested dep resolved ajv@6, causing webpack to crash on start with `Cannot find module ajv/dist/compile/codegen`. Added overrides.ajv (npm) + resolutions.ajv (yarn) both set to ^8.20.0 to force v8 across the dep tree. | F36: frontend/package.json (overrides + resolutions blocks) | G36: manual: npm ls ajv shows ajv@8.20.0 at root + ajv-keywords@5.1.0 -> ajv@8 deduped | H36: Done | I36: P0 | J36: 2026-08-09 | K36: 2026-08-09 | L36: 5a4644e | M36: Value must match the direct dep pinning exactly (^8.20.0) or npm throws EOVERRIDE. Learned that mid-fix.
A37: Status legend:
A38: Not Started | B38: In backlog, no work yet
A39: Planning | B39: Reading code, scoping the fix, drafting approach
A40: In Progress | B40: Writing the fix
A41: Code Review | B41: Fix written, awaiting review / self-review
A42: Testing | B42: Tests running
A43: Done | B43: Merged + tests green + verified
A44: Blocked | B44: Waiting on external dependency or decision
A45: Rolled Back | B45: Shipped, broke something, reverted (record, don't hide)
A46: FIX-FUP-15 | B46: Follow-up (from FIX-002-F) | C46: (logged during 002-F QA) | D46: Wire `docker build` into CI (real container smoke test) | E46: FIX-002-F ships 25 static contract tests on the Dockerfile because Docker daemon isn't available in this test environment. That's fine as a first line of defense but doesn't catch runtime failures (missing apt package, wheel install failing, base-image tag drift). Once CI is stood up (S5-06), a job should build the image, run `docker run --rm ... /api/health`, and gate merges on it. | F46: (CI config; new; blocked on S5-06 CI/CD setup) | G46: smoke: docker build succeeds + healthcheck returns 200 in <60s | H46: Not Started | I46: P1 | M46: Depends on S5-06 (Stand up CI/CD). Until then, the static tests are the guardrail.
A47: FIX-003-A | B47: Sprint 2 / Tenancy & Data | C47: S2-03 + S2-04 | D47: Tenant-scope OTP + WhatsApp phone routing | E47: Phone was treated as a global identifier. Two users in different tenants sharing a phone collided: OTP overwrote each other's codes; verify returned first-match user across tenants; resolve_wa_tenant silently orphaned the losing tenant's user by marking them wa_phone_obsolete. Also folded S2-04: whatsapp_logs OR-included tenant_id=None events, leaking platform-wide unrouted traffic into every tenant's log view. Fix: phone is unique WITHIN a tenant. New services/phone.find_tenant_choices_for_phone as single choke-point. OTP models accept optional tenant_id; single-tenant fast path unchanged, multi-tenant returns ambiguity payload (200 for request, 409 for verify). otp_codes now keyed by (phone, tenant_id) with new compound unique index + migration otp_codes_tenant_scope_v1. resolve_wa_tenant cross-tenant collision: notifies BOTH tenant owners, falls back to WA_TENANT_ID, does NOT mark anyone obsolete. Within-tenant dedup still works with defense-in-depth tenant_id guard on update_many. whatsapp_logs strict tenant_id filter. | F47: services/phone.py (find_tenant_choices_for_phone); server.py: OtpRequestInput/OtpVerifyInput (tenant_id field), _issue_otp (compound key + required tenant_id), /auth/otp/request (ambiguity + tenant_id validation), /auth/otp/verify (compound key + 409 ambiguity), /auth/invite/{token}/start (uses invite's tenant), resolve_wa_tenant (cross-tenant safety + tenant-guarded update_many + invited_employees safety), whatsapp_logs (strict filter), _bootstrap (new migration + compound index) | G47: tests/test_tenant_phone_routing.py - 22 tests (helper contract, OTP model + handler source-level invariants, resolve_wa_tenant cross-tenant safety across 7 scenarios, whatsapp_logs regression guard, bootstrap wiring) | H47: Done | I47: P0 | J47: 2026-08-09 | K47: 2026-08-09 | L47: 6a1ecec | M47: Bundles S2-03 (P0) with S2-04 (P1) since they share the same code area. Handler source-level assertions are the primary lock-in; live-HTTP integration tests (test_iteration29/30) run only in the deployed env — logged as FIX-FUP-16. Per-tenant WABA is Sprint 3 (FIX-FUP-17).
A48: FIX-FUP-16 | B48: Follow-up (from FIX-003-A) | C48: (logged during 003-A) | D48: Update deployed integration tests to send tenant_id on OTP flows | E48: tests/test_iteration29.py + test_iteration30.py are live-HTTP tests against /app/backend/.env (Linux paths, deployed-only). They hit /auth/otp/request + /auth/otp/verify without tenant_id. In a single-tenant deployed env they still pass (fast path), but a multi-tenant fixture would need tenant_id threading. Update once a staging env with multiple tenants is available. | F48: tests/test_iteration29.py, tests/test_iteration30.py | G48: test: multi-tenant OTP flow with tenant_id param passes | H48: Not Started | I48: P2 | M48: Blocked on S5-01 (Stand up staging env). Single-tenant deployments unaffected.
A49: FIX-FUP-17 | B49: Follow-up (from FIX-003-A) | C49: (logged during 003-A) | D49: Per-tenant WhatsApp Business Account (WABA) provisioning | E49: Today WA_PHONE_NUMBER_ID is a platform-level env var. That means the whole platform runs against ONE Meta WABA and sender-phone is the only signal we have for tenant routing. If each tenant provisions their OWN WABA + business number, we can route by the RECEIVING business number (which Meta sends in webhook value.metadata.phone_number_id) instead of the sender's phone. Eliminates cross-tenant collisions entirely — a phone can be an employee in workspace A and a supplier in workspace B without ambiguity because Meta tells us which of OUR numbers the message hit. Requires: schema change (tenants.wa_phone_number_id), settings UI, onboarding flow to link a Meta WABA, and updating resolve_wa_tenant to prefer receiving-number lookup. | F49: server.py resolve_wa_tenant (add receiving_pnid arg); routers/tenant (settings UI to save wa_phone_number_id); webhook to extract value.metadata.phone_number_id and pass through | G49: test: two tenants with distinct wa_phone_number_id -> messages route correctly; same sender phone across both -> each tenant gets their own message | H49: Not Started | I49: P1 | M49: Sprint 3 territory (S3-03 or new S3-05). Removes the whole class of cross-tenant WhatsApp collision.
A50: FIX-003-B | B50: Sprint 2 / Tenancy Hygiene | C50: S2-05 + S2-08 + S2-10 + S2-12 | D50: Sprint 2 hygiene batch: enrich_decisions tenant guard, contacts.type index, register race, active-workflow lock-in | E50: S2-05 defense-in-depth: enrich_decision(s) now filter task_ids/created_by lookups by tenant_id; batch inference for single-tenant callers who forget; explicit at all 6 caller sites. S2-08: contacts index was on dead field `kind` (the collection uses `type`); replaced + drops legacy. S2-10: register handler was find_one-then-insert_one with orphan-tenant risk on concurrent race; now catches DuplicateKeyError, rolls back the orphan tenant, returns friendly 400. S2-12: verified S2-12 was fully closed by FIX-001-F and locked it in with a regression test guarding against ['delivered','paid'] reappearing anywhere in server.py. | F50: server.py (enrich_decision(s) + know360 caller + owner_brief caller + contacts index in bootstrap); routers/decisions.py (6 enrich_decision callers); routers/brief.py (awaiting_approval); routers/auth.py (register DuplicateKeyError handling + orphan tenant rollback) | G50: tests/test_tenancy_hygiene_batch.py - 10 tests (4x enrich_decision tenant guard incl. batch inference + mixed-batch + creator lookup, 2x contacts.type index bootstrap, 2x register DuplicateKeyError + rollback + email unique index invariant, 2x active-workflow lock-in) | H50: Done | I50: P1 | J50: 2026-08-10 | K50: 2026-08-10 | L50: f18bbc3 | M50: Bundled 4 small Sprint 2 items. All P1/P2, no go-live blocker individually; bundled for efficiency. S2-12 was already implemented by FIX-001-F; this ship formalized the regression guard.
A51: FIX-003-C | B51: Sprint 2 / Auth & Hygiene | C51: S2-06 + S2-09 + S2-11 | D51: JWT revocation on logout + contact rename cascade + AI regen failure flag | E51: S2-06 (security): /logout only cleared browser cookie; JWT stayed valid until exp (7 days). Now: every access token gains a random jti; /logout records (jti, exp) in db.revoked_tokens; get_current_user checks is_revoked on every authenticated request. TTL index on revoked_tokens.exp keeps the table bounded. Fail-open on Mongo blip so a transient DB error doesn't lock everyone out. /logout has no auth dependency so a corrupted/already-revoked token can still clear the cookie. S2-09: contact_name is denormalized into invoices/payments/workflows.counterparty; renaming a contact left every existing row with stale display + search columns. update_contact now cascades: match by contact_id (recent rows) + fall back to exact old_name where contact_id is null (legacy rows). Every cascade update is tenant-scoped. S2-11: regenerate_operating_model + regenerate_finance_categories called AI generators directly, so silent AI degradation (timeout, malformed JSON, empty pipelines) left tenants with default configs and no signal. Now uses ai_setup._with_status wrappers, persists ai_setup_status on tenant, returns ai_setup_status_summary in response. On defaulted/failed run, preserves existing config instead of clobbering. | F51: services/session_revocation.py (new: revoke/is_revoked with fail-open); core.py (create_token adds jti, get_current_user checks is_revoked); routers/auth.py (/logout revokes current jti + Request import); server.py (bootstrap: revoked_tokens jti unique + exp TTL indexes; regenerate_operating_model + regenerate_finance_categories status-tracking; update_contact rename cascade) | G51: tests/test_session_revocation.py - 17 tests (6 revoke/is_revoked contract, 2 jti in create_token, 2 /logout revocation + no auth dep, 1 get_current_user revocation check, 1 bootstrap indexes, 2 contact rename cascade guards, 3 AI regen status tracking) | H51: Done | I51: P1 | J51: 2026-08-10 | K51: 2026-08-10 | L51: f48bd24 | M51: S2-06 is the real security fix in this batch. Sprint 2 now 11/12 shipped; only S2-07 (email verification + password reset, green-field email service) remains.
A52: FIX-003-D | B52: Sprint 2 / Email + Auth | C52: S2-07 | D52: Email verification + password reset (green-field) | E52: New auth flows built from scratch. services/auth_emails.py provides a single token model for both flows: auth_email_tokens keyed by URL-safe 32-char token (secrets.token_urlsafe(24) = ~192 bits entropy), single-use consume() with atomic filter on used_at:None, issue() idempotent within cooldown to prevent inbox flood. TTLs differ by kind: email_verify=3 days, password_reset=1 hour. 4 endpoints on routers/auth.py: POST /auth/email/send-verification (authenticated), GET /auth/email/verify/{token} (public), POST /auth/password/forgot (public, canonical response = no email enumeration), POST /auth/password/reset (public, single-use + invalidates sibling reset tokens). Register hook: verification email sent best-effort on /auth/register (SMTP down never fails registration). 3 bootstrap indexes: token unique, expires_at TTL, kind+email+used_at compound for issue reuse lookup. Passwordless (OTP-only) accounts get canonical /forgot response but no email + explicit refusal on /reset. | F52: services/auth_emails.py (new: token model + email templates); routers/auth.py (PasswordForgotInput/PasswordResetInput models, 4 new endpoints, register hook, _app_base_url helper); server.py (3 auth_email_tokens indexes in bootstrap) | G52: tests/test_email_verification_and_reset.py - 23 tests (8 issue contract, 5 consume single-use + failure modes, 1 invalidate isolation, 5 endpoint shape guards, 1 register best-effort, 1 bootstrap indexes, 2 email templates) | H52: Done | I52: P1 | J52: 2026-08-10 | K52: 2026-08-10 | L52: 4ef865e | M52: SPRINT 2 COMPLETE (12/12). Green-field build. Follow-ups: FIX-FUP-18 per-IP rate limit on /forgot; FIX-FUP-19 frontend /verify-email + /reset-password pages.
A53: FIX-FUP-18 | B53: Follow-up (from FIX-003-D) | C53: (logged during 003-D) | D53: Per-IP rate limit on /auth/password/forgot | E53: Today the throttle is per-account via services.auth_emails.issue() cooldown (60s). That prevents inbox spam for one target, but an attacker cycling emails can still overwhelm SMTP quota. Add IP-based rate limit (e.g. 10 requests/hour) via a middleware or a small in-process counter. | F53: middleware or routers/auth.py | G53: test: 11 rapid requests from same IP -> 11th returns 429 | H53: Not Started | I53: P2 | M53: Sprint 0/security territory; not a go-live blocker for controlled beta.
A54: FIX-FUP-19 | B54: Follow-up (from FIX-003-D) | C54: (logged during 003-D) | D54: Frontend pages: /verify-email + /reset-password | E54: Backend links point at APP_BASE_URL/verify-email?token=... and APP_BASE_URL/reset-password?token=... but no frontend routes exist yet. Add: two lightweight pages that read the token from the query string, call GET /api/auth/email/verify/{token} or POST /api/auth/password/reset respectively, and show success/error UI. | F54: frontend/src/App.js routes; new components | G54: manual: click a verification email link -> success page renders | H54: Not Started | I54: P1 | M54: Backend is complete and callable via curl; frontend pages are the last mile for users.
A55: FIX-004-A | B55: Sprint 2.5 / RBAC Wave 1 | C55: RBAC-01 + RBAC-02 + RBAC-03 | D55: RBAC Wave 1: HMAC-signed drafts + CAPTCHA/rate-limit register + SSRF-guarded signup AI | E55: 3 P0 public-endpoint gaps closed. RBAC-01: onboarding drafts were world-accessible by ID; now HMAC-signed X-Draft-Token required on GET/PATCH + per-IP rate limit on create. RBAC-02: /register was unauth + unlimited; now Turnstile/hCaptcha token verification + 3/hour/IP rate limit. RBAC-03: signup AI endpoints (website-intel, tts, stt, interview/*) were unauth credit-burners; now shared _guard_signup_endpoint dep runs hourly (30/IP) + burst (5/10s) rate-limit + CAPTCHA. website-intel gains SSRF guard blocking private v4/v6 ranges, loopback, link-local, cloud-metadata IPs (169.254.169.254), and non-http(s) schemes. Also introduces reusable infra: services/rate_limit.py (sliding-window, fail-open), services/captcha.py (Turnstile/hCaptcha with 3 env states), services/ssrf_guard.py (single choke-point URL validator), services/auth/draft_tokens.py (HMAC sign/verify). All will be reused by RBAC Waves 2-5. | F55: services/rate_limit.py (new); services/captcha.py (new); services/ssrf_guard.py (new); services/auth/draft_tokens.py (new); services/auth/__init__.py (exports); routers/onboarding.py (draft token + rate limit); routers/auth.py (register captcha + rate limit); routers/signup.py (guard + SSRF on 9 endpoints) | G55: tests/test_rbac_wave1.py - 41 tests (9 rate_limit contract + client_ip variants, 5 captcha env-state combos, 10 SSRF guard incl. v6 loopback + link-local, 7 draft tokens, 5 onboarding gate, 2 register gate, 3 signup AI gate) | H55: Done | I55: P0 | J55: 2026-08-10 | K55: 2026-08-10 | L55: a44135f | M55: Backend-complete. FIX-FUP-20 tracks the frontend integration (Turnstile widget, X-Draft-Token header, X-Captcha-Token header). Rate limiter is per-worker; Redis backend logged as FIX-FUP-21 for multi-worker deploys.
A56: FIX-FUP-20 | B56: Follow-up (from FIX-004-A) | C56: (logged during Wave 1) | D56: Frontend integration for RBAC Wave 1 (CAPTCHA widget + auth headers) | E56: Backend is complete but the frontend needs 3 updates: (a) onboarding wizard stores the draft_token returned from POST /onboarding/draft, sends X-Draft-Token on every subsequent GET/PATCH; (b) /register page renders a Cloudflare Turnstile widget (free, invisible for most users), passes the resulting captcha_token in the request body; (c) /signup wizard renders same widget on first AI call per session, passes the resulting token via X-Captcha-Token header. Without these, the frontend will fail against a prod backend that has CAPTCHA_REQUIRED=1. | F56: frontend/src pages: OnboardingWizard, Register, Signup | G56: manual: form submits succeed; loading Turnstile in dev works | H56: Not Started | I56: P1 | M56: Backend is deployed-ready in permissive mode today; frontend fix required before flipping CAPTCHA_REQUIRED=1 in prod.
A57: FIX-FUP-21 | B57: Follow-up (from FIX-004-A) | C57: (logged during Wave 1) | D57: Cross-process rate limiter (Redis backend) | E57: Current services/rate_limit.py is in-process. With N uvicorn workers the effective per-IP ceiling is N*cap. Fine for the current unauth surface (a bot burst is spread across workers roughly evenly), but not correct. Replace with a Redis-backed sliding window using INCR + EXPIRE or a Lua script. Same public API so no caller changes. | F57: services/rate_limit.py | G57: test: 3-worker simulation, verify shared counter | H57: Not Started | I57: P2 | M57: Sprint 3+ territory when we scale beyond 1 worker per instance.
A58: FIX-FUP-22 | B58: Follow-up (from FIX-004-A) | C58: (logged during Wave 1) | D58: SSRF guard v2: pin resolved IP through httpx transport | E58: Current is_url_safe_for_fetch resolves hostname + checks IPs, then httpx.get re-resolves independently. In the ~100ms gap between check + fetch, a hostile DNS server could re-flip the record from public to private. Fix: use httpx transport with a custom Resolver that reuses the resolved IPs from is_url_safe_for_fetch (or pass resolved IP + Host header separately). Adds SNI + Host complexity. | F58: services/ssrf_guard.py, routers/signup.py | G58: test: TOCTOU race simulator with a mock resolver flipping IPs mid-call | H58: Not Started | I58: P2 | M58: Current guard is fine for the SME-scale threat model; hardening is nice-to-have.
A59: FIX-004-B | B59: Sprint 2.5 / RBAC Wave 2 | C59: RBAC-12 + RBAC-13 | D59: Memberships collection + email-per-person (many-to-many user↔tenant) | E59: Big data-model refactor that unblocks every remaining multi-workspace fix. Before: user.tenant_id single FK + users.email globally unique = one email = one person = one workspace forever. After: new memberships collection (user_id, tenant_id, role, permissions, status, invite metadata) with compound unique. users.email still globally unique (one PERSON per email) but that person can belong to N workspaces via N membership rows. Unlocks accountants serving multiple SMEs, founders with 2 businesses, employee invited to 2nd workspace. get_current_user projects role/permissions from CURRENT membership onto user dict — ~430 downstream call sites keep working unchanged (compat layer). Only login + register + user CRUD + invite flow have real logic changes. Bootstrap: 3 new indexes + backfill_memberships_v1 migration (via FIX-002-C ledger). New endpoints: GET /me/workspaces + POST /me/switch-workspace. Login gains optional tenant_id in body; multi-membership + no hint returns ambiguity payload for the frontend picker. | F59: services/auth/membership.py (new: full service + compat helper); services/auth/__init__.py (exports); core.py (get_current_user resolves membership + projects onto user + legacy fallback); server.py (bootstrap: 3 indexes + backfill migration); routers/auth.py (register creates owner membership + rollback; login ambiguity; /me/workspaces; /me/switch-workspace); routers/team.py (create_user creates membership; update_user mirrors role/perm changes) | G59: tests/test_memberships_wave2.py — 29 tests (5 create incl. idempotent + reactivate, 2 find + status filter, 2 list-for-user, 3 resolve_login_choices, 2 update, 2 remove soft-delete, 2 project, 1 bootstrap, 1 register+rollback, 2 login flow, 3 workspace endpoints, 2 get_current_user, 2 team mirroring) | H59: Done | I59: P0 | J59: 2026-08-10 | K59: 2026-08-10 | L59: 56399d6 | M59: Blocks-go-live P0. Sprint 2.5 now 5/20 shipped (Waves 1 + 2). Compat layer keeps 349/349 offline regression green — downstream refactor is optional and can happen incrementally. Frontend integration (workspace switcher UI, ambiguity picker on login) is FIX-FUP-25.
A60: FIX-FUP-23 | B60: Follow-up (from FIX-004-B) | C60: (logged during Wave 2) | D60: OTP verify: read role from membership directly (not via compat) | E60: Today OTP verify still reads user.role via the get_current_user compat layer projection. Correct behavior, but the code reads clearer if we look up the membership explicitly for role. Small cleanup — trivial once every downstream reader is migrated off user.tenant_id/role. | F60: server.py verify_otp handler | G60: test: OTP verify returns correct role when user has multi-tenant | H60: Not Started | I60: P2 | M60: Cosmetic; correct behavior today.
A61: FIX-FUP-24 | B61: Follow-up (from FIX-004-B) | C61: (logged during Wave 2) | D61: Cascade: delete memberships on user delete | E61: Currently memberships are soft-deleted (status=removed) when a tenant admin removes an employee. There's no path yet to delete the USER (person) — that comes with RBAC-22 (off-boarding wizard) in Wave 4. When we get there, need to decide: delete all their memberships? preserve for audit? Also cascade rules if a TENANT is deleted (currently TENANT_COLLECTIONS wipe should include memberships). | F61: routers/admin.py TENANT_COLLECTIONS, routers/team.py user delete path | G61: test: tenant delete wipes all memberships for that tenant | H61: Not Started | I61: P1 | M61: Blocks RBAC-22 off-boarding (Wave 4).
A62: FIX-FUP-25 | B62: Follow-up (from FIX-004-B) | C62: (logged during Wave 2) | D62: Frontend: workspace switcher UI + login ambiguity picker | E62: Backend is ready. Frontend needs: (a) login page handles the {ambiguous: true, choices: [...]} response and renders a workspace-picker; (b) top-bar workspace switcher calls GET /me/workspaces and POST /me/switch-workspace; (c) invited-user landing UI (post-OTP) if a person now holds multiple memberships. Also update the frontend register form: when a user with an existing email hits /register, show the friendly 'log in first + then Settings > Create Workspace' message. | F62: frontend/src pages: Login, TopBar, Settings, Register | G62: manual: log in as user with 2 memberships, verify picker + switch | H62: Not Started | I62: P1 | M62: Backend accepts current single-membership frontend unchanged; frontend can ship this incrementally.
A63: FIX-004-C | B63: Sprint 2.5 / RBAC Wave 3 sub-batch A | C63: RBAC-04..11 (8 items) | D63: Wave 3 endpoint gates: 8 auth-only endpoints upgraded to role/perm gated | E63: Closes every 'auth-only endpoint that should be role/perm-gated' finding from the RBAC audit sweep. 8 items in one commit because they share the same testing infrastructure (cross-role permission matrix). RBAC-04 /workflows POST -> require_perm(workflows) [symmetric with DELETE which was already owner]. RBAC-05 /captures/{id}/approve|reject|reassign|clarify -> require_perm(approvals). RBAC-06 /follow-up/run -> require_perm(team_manage). RBAC-07 4 of 17 tasks endpoints upgraded (delete_task role(owner), reassign/delete-plan/prioritize require_perm(team_manage)); other 13 remain auth-only with inline scope checks because widening would break normal workflow. RBAC-08 /meetings + /meetings/text -> require_perm(voice_capture) [matches /voice-notes]. RBAC-09 /leaves approve/reject/request-info -> require_perm(leave_approve) [decorator gate; inline _can_approve_leave stays as defense-in-depth]. RBAC-10 /brain/export -> require_perm(brain_export) [NEW permission key added to config; NOT in _BASE_PERMS so owner-only or explicit grant]. RBAC-11 /memory POST -> require_perm(brain) [read stays open]. | F63: config.py (brain_export in PERMISSION_KEYS); server.py (create_workflow, 4 captures, followup_run, 2 meetings, add_memory); routers/tasks.py (delete_task, reassign_task, delete_execution_plan, prioritize_tasks + require_role/require_perm imports); routers/team.py (3 leaves endpoints); routers/brain.py (/brain/export) | G63: tests/test_rbac_wave3_gates.py — 22 tests (3 config lock-in incl. brain_export not-in-base, 11 per-endpoint dep verification for all 8 RBAC-IDs, 6 cross-role permission matrix incl. owner all-perms + sales/finance defaults + custom role fallback + explicit grant override + brain_export explicit-grant-only, 2 regression on existing gates) | H63: Done | I63: P1 | J63: 2026-08-10 | K63: 2026-08-10 | L63: 9b3a1c3 | M63: Sprint 2.5 now 13/20 shipped (Waves 1+2 + Wave 3 sub-batch A). Sub-batches B (per-role perm editor + owner exclusion + ROLES fix) and C (pending-invite visibility) remain. Cross-role matrix test is the regression harness — any new endpoint added later must add a matrix row.
A64: FIX-004-D | B64: Sprint 2.5 / RBAC Wave 3 sub-batch B | C64: RBAC-14 + RBAC-15 + RBAC-16 | D64: Role model: per-role permission editor + owner exclusions + production→operations canonical rename | E64: Wave 2 memberships made these possible; this fix ships them. RBAC-14: tenant.roles[i].permissions[] carries role-level perms. NEW endpoint PATCH /tenant/roles/{key}/permissions (team_manage). user_perms() 5-tier precedence: owner all-minus-exclusions -> user override -> tenant role map -> ROLE_DEFAULT_PERMS -> _BASE_PERMS. Custom roles ('warehouse_manager') can now carry finance/ledger/team_manage etc. without editing each user individually — a role is a policy unit again. RBAC-15: tenant.owner_exclusions:[str] lets a tenant deny specific perms to owner(s). NEW endpoint PUT /tenant/owner-exclusions (owner-only). Backward compat: empty list = classic all-perms owner. Solves 'co-founder with everything except finance visibility'. RBAC-16: canonical role name = 'operations' (matches DEFAULT_ROLES). config.ROLES rewritten. Bootstrap migration rename_production_role_v1 (via FIX-002-C ledger) rewrites tenant.roles[].key + users.role + memberships.role. Idempotent. | F64: config.py (ROLES canonical); core.py (get_current_user fetches tenant roles + owner_exclusions + populates _role_perms_map/_owner_exclusions on user; user_perms rewritten with 5-tier precedence); server.py (2 new endpoints: PATCH /tenant/roles/{key}/permissions + PUT /tenant/owner-exclusions; bootstrap rename_production_role_v1 migration) | G64: tests/test_rbac_wave3_role_model.py — 16 tests (8 per-role perms incl. precedence + endpoint gates, 5 owner exclusions incl. backward compat + PUT semantic + owner-only, 2 canonical rename + migration wiring, 1 get_current_user enrichment) | H64: Done | I64: P1 | J64: 2026-08-10 | K64: 2026-08-10 | L64: f440c33 | M64: Sprint 2.5 now 16/20 shipped (Waves 1+2 + Wave 3 A+B). Only Wave 3 sub-batch C (RBAC-17) remains in Wave 3. Frontend Settings UI logged as FIX-FUP-26.
A65: FIX-FUP-26 | B65: Follow-up (from FIX-004-D) | C65: (logged during Wave 3-B) | D65: Frontend Settings UI: per-role permission editor + owner exclusions | E65: Backend endpoints ship in FIX-004-D. Frontend needs: (a) Team & Roles settings page adds a permission-checkbox matrix per tenant role, POSTs to PATCH /tenant/roles/{key}/permissions; (b) Owner settings page adds an exclusion-checkbox list, PUTs to /tenant/owner-exclusions. Admins can already call the endpoints via curl but the UX story isn't complete until the UI ships. | F65: frontend/src pages: Settings, Team, Roles | G65: manual: edit a role's perms in UI, verify a member's effective perms reflect the change on next request | H65: Not Started | I65: P1 | M65: Backend is deploy-ready; UI blocks non-technical admin usage.
A66: FIX-004-E | B66: Sprint 2.5 / RBAC Wave 3 sub-batch C | C66: RBAC-17 | D66: Pending-invite visibility on GET /users + POST /users/{id}/uninvite | E66: Small ship that surfaces what Wave 2 already made possible. GET /users now merges membership.status onto each user (pending|active|suspended|removed excluded) + invited_at + accepted_at so admin UI can render a Pending badge. Legacy users without membership rows default to 'active'. NEW endpoint POST /users/{id}/uninvite (team_manage) revokes a pending invite: soft-deletes membership + wipes invite_token on user doc so the invite URL stops resolving. Refuses non-pending targets (use suspend/delete instead). Emits log_activity('user_uninvited'). | F66: routers/team.py (list_users enrichment + new uninvite_user endpoint) | G66: tests/test_rbac_wave3_invite_status.py — 8 tests (3 list enrichment, 5 uninvite gate/refusal/token-invalidation/logging) | H66: Done | I66: P1 | J66: 2026-08-10 | K66: 2026-08-10 | L66: 1541439 | M66: Sprint 2.5 now 17/20 shipped. RBAC Wave 3 COMPLETE. Remaining: RBAC-18 department scope (Sprint 4), RBAC-19 user groups (Sprint 4), RBAC-30 customer portal (Sprint 5).
A67: FIX-004-F | B67: Sprint 2.5 / RBAC Wave 4-A | C67: RBAC-20 | D67: Immutable audit log (SOC2/DPDP/GDPR compliance) | E67: New services/audit_log.py: append-only, best-effort record() + tenant-scoped query() + context_from() request/user extractor. Fail-open by design — Mongo hiccup during audit write must not fail user action. NEVER raises. 35 canonical action names in ACTIONS registry for review-time typo catch. Bootstrap creates 3 indexes: (tenant_id, ts DESC), (actor_id, ts DESC), (tenant_id, entity_type, entity_id). NO TTL (rows live forever for compliance). NO PATCH/DELETE endpoints — API-layer append-only; tampering requires DB access. GET /admin/audit-log endpoint (owner-only) supports action/actor_id/entity_type/entity_id/since_ts/before_ts filters + limit (capped 500) + cursor paging. High-value events wired to record() this ship: login_success + login_failure (captures attempted email on unknown user), logout (records even on invalid token), tenant_created + user_created on register, owner_exclusions_updated with before/after diff. Expanding call-site coverage to user_deleted / role_deleted / decision_approved / etc. logged as FIX-FUP-27 — 3-line change per event, non-blocker. | F67: services/audit_log.py (new); server.py (bootstrap: 3 indexes + GET /admin/audit-log endpoint + owner_exclusions audit wire); routers/auth.py (login success + failure audit, logout audit, register tenant+user audit) | G67: tests/test_audit_log.py — 24 tests (5 record contract incl. fail-open + string caps, 6 query contract incl. tenant isolation + paging, 4 context_from variants, 1 bootstrap, 3 endpoint incl. no-PATCH/DELETE guard, 5 wire-up on login/logout/register/owner-exclusions) | H67: Done | I67: P0 | J67: 2026-08-10 | K67: 2026-08-10 | L67: cc7c698 | M67: Sprint 2.5 now 18/20 shipped. Wave 4 sub-batch 1/3 done — sub-batches G (session mgmt UI, RBAC-21) and H (off-boarding wizard, RBAC-22) remain. Blocks-go-live P0 requirement for SOC 2 / DPDP compliance now met.
A68: FIX-FUP-27 | B68: Follow-up (from FIX-004-F) | C68: (logged during Wave 4-A) | D68: Expand audit_log.record() call-site coverage across mutating events | E68: Wave 4-A ships the audit-log service + 4 high-value event call sites (login, logout, register, owner-exclusions). Progressive coverage needed on the rest of the ACTIONS registry: user_deleted, user_uninvited, role_deleted, role_permissions_updated, decision_approved/rejected, capture_approved/rejected, workflow_deleted, task_deleted, tenant_deleted (from admin.py), platform_admin_tenant_wipe, ai_key_updated. Each is a 3-line change: audit_log.context_from(request, user) + await record(db, action='...', entity_type='...', entity_id='...', before/after, **ctx). Non-blocker — infra is ready, incremental fill-in. | F68: routers/admin.py, routers/team.py, routers/decisions.py, routers/tasks.py, server.py | G68: test: each new call site verified via grep + one integration assertion per event | H68: Not Started | I68: P1 | M68: Post-FIX-004-F incremental. Ship as batches of 3-4 events per commit.
A69: FIX-FUP-28 | B69: Follow-up (from FIX-004-F) | C69: (logged during Wave 4-A) | D69: Audit log retention policy (TTL + off-hot-storage archive) | E69: Currently audit_log has NO TTL — rows live forever. Compliance regimes (SOC 2, DPDP) require min retention (12-24 months typically) but max retention is a business decision (privacy vs forensics tradeoff). Also: hot Mongo isn't the cheapest place to keep 5-year audit history. Plan an archive path: TTL on hot rows + cold storage (S3 / obj_store) for archived tail. Blocks nothing today; revisit before we sell to a customer whose contract requires a retention SLA. | F69: services/audit_log.py + scheduler job + obj_store integration | G69: test: TTL wipes rows past retention window; archive job moves them intact | H69: Not Started | I69: P2 | M69: Sprint 5 (DevOps + compliance) territory.
A70: FIX-004-G | B70: Sprint 2.5 / RBAC Wave 4-B | C70: RBAC-21 | D70: Session-management UI (/me/sessions list + revoke by device) | E70: New services/auth/session_tracking.py extends the FIX-003-C revocation infra with device metadata (ua, ip, last_seen_at). NEW active_sessions collection with jti unique index + user_id/created_at index + exp TTL for auto-purge. record_session/touch_session/list_sessions/revoke_one_session/revoke_all_sessions_for_user (with tenant_id + keep_jti knobs). get_current_user gained touch_session call so /me/sessions shows accurate last-seen. login + register + switch-workspace all record the new jti. 3 new endpoints: GET /me/sessions (marks current session), DELETE /me/sessions/{jti} (ownership-guarded), DELETE /me/sessions (revoke all except current). | F70: services/auth/session_tracking.py (new); services/auth/__init__.py (exports); core.py (get_current_user calls touch_session); server.py (bootstrap: 3 active_sessions indexes); routers/auth.py (login + register + switch-workspace record + 3 new endpoints) | G70: tests/test_session_mgmt.py — 20 tests (4 record contract incl. fail-open + UA cap, 3 list incl. user isolation + tenant filter, 3 revoke_one incl. ownership guard, 2 revoke_all incl. keep_jti + tenant filter, 1 bootstrap indexes, 3 endpoint source guards, 1 get_current_user touch, 3 wire-up on login/register/switch) | H70: Done | I70: P0 | J70: 2026-08-10 | K70: 2026-08-10 | L70: d95ae44 | M70: Sprint 2.5: 19/20. Only RBAC-22 (off-boarding wizard) left. Backend done — frontend /settings/sessions UI logged as FIX-FUP-29.
A71: FIX-FUP-29 | B71: Follow-up (from FIX-004-G) | C71: (logged during Wave 4-B) | D71: Frontend Settings > Sessions UI | E71: Backend ships GET/DELETE /me/sessions + DELETE /me/sessions/{jti}. Frontend needs Settings page listing sessions with UA/IP/last-seen + revoke buttons (individual + 'sign out other devices'). Row for current session should be marked distinct (grey out revoke). | F71: frontend/src pages: Settings/Sessions | G71: manual: log in on 2 devices, revoke the other from device 1, verify device 2 401s | H71: Not Started | I71: P1 | M71: Backend deploy-ready; UI blocks user self-serve session control.
A72: FIX-004-H | B72: Sprint 2.5 / RBAC Wave 4-C | C72: RBAC-22 | D72: Off-boarding wizard (deprovisioning) — RBAC Wave 4 COMPLETE | E72: New services/deprovisioning.py orchestrates 6 idempotent steps into one call: last-owner guard + tenant-scoped session revoke + soft-remove membership + invalidate invite_token + reassign owned tasks + reassign authored contacts + audit_log entry. New endpoint POST /users/{id}/deprovision {reassign_to_user_id?} — owner-only. Self-deprovision refused. Replacement user validated as LIVE member. Returns per-step report for UI confirmation. Session revoke is TENANT-SCOPED — a user's sessions in other tenants they belong to survive. Task reassignment updates denormalized assignee_role. No reassign target = null the fields. | F72: services/deprovisioning.py (new); routers/team.py (new POST /users/{id}/deprovision endpoint + DeprovisionInput model + BaseModel import) | G72: tests/test_deprovisioning.py — 11 tests (2 fresh full-run with + without replacement, 1 idempotent, 2 last-owner guard, 1 tenant scoping, 1 audit entry, 4 endpoint gates) | H72: Done | I72: P0 | J72: 2026-08-10 | K72: 2026-08-10 | L72: 309ef84 | M72: RBAC WAVE 4 COMPLETE — 3/3 sub-batches shipped (F+G+H). Sprint 2.5 now 20/20. Full RBAC roadmap Waves 1-4 COMPLETE — 20 of 30 audit items shipped. Remaining 10 are Sprint 4/5 items: RBAC-18 (department scope), RBAC-19 (user groups), RBAC-23..28 (2FA, ownership transfer, DPDP consent, delegation, time-bounded perms, SSO, API keys), RBAC-30 (customer portal).
A73: FIX-FUP-30 | B73: Follow-up (from FIX-004-H) | C73: (logged during Wave 4-C) | D73: Ownership transfer wizard (owner-to-owner) | E73: Deprovisioning's last-owner guard is correct behavior — it blocks removing the only owner. But it leaves no path out. Need a separate 'transfer ownership' flow: promote another member to owner, then optionally deprovision the previous owner. 2FA confirmation recommended for the promoting owner. | F73: new endpoint POST /tenant/transfer-ownership + service | G73: test: two-owner state achieved, previous owner deprovisions cleanly | H73: Not Started | I73: P1 | M73: RBAC-24 in the audit — Sprint 3 territory.
A74: FIX-FUP-31 | B74: Follow-up (from FIX-004-H) | C74: (logged during Wave 4-C) | D74: Cascade decisions in deprovision | E74: Today deprovision reassigns tasks + contacts but NOT decisions where created_by = target. Small addition — same pattern as tasks. Decision-approver relationships also worth considering: if target was designated approver for pending decisions, they need routing to the replacement. | F74: services/deprovisioning.py | G74: test: fresh deprovision reassigns created_by decisions + approver_id decisions | H74: Not Started | I74: P2 | M74: Incremental improvement on FIX-004-H.
A75: FIX-FUP-32 | B75: Follow-up (from FIX-004-H) | C75: (logged during Wave 4-C) | D75: Frontend off-boarding wizard UI | E75: Backend done. Frontend needs: Team > Member detail page adds 'Remove from workspace' button that opens a wizard: pick replacement member (dropdown of live members), preview count of items to reassign, confirm modal, POST /users/{id}/deprovision, show report summary. | F75: frontend/src pages: Team/MemberDetail, Team/OffboardWizard | G75: manual: off-board a test member, verify counts match backend report | H75: Not Started | I75: P1 | M75: Backend deploy-ready via curl.
A76: FIX-005-A | B76: Sprint 3 / Billing + AI Keys | C76: S3-02 + S3-03 | D76: Plan/entitlement fields + per-tenant AI keys | E76: Two Sprint 3 items shipped together — both pure data-model + resolver changes, no external integration. S3-02: services/plans.py with 5 plans (trial/starter/business/enterprise/grandfathered), each carries seat_limit + quotas (llm_tokens/stt_minutes/storage/brain_docs) + features (whatsapp/sso/api_keys). effective_plan(tenant) merges base + tenant overrides. new_tenant_plan_fields() called in register for trial+14d. enforce_seat_limit raises 402 with upgrade prompt. Bootstrap migration backfill_grandfathered_plans_v1 marks pre-plan tenants — same generous shape as business, retained forever, zero user-visible change. team.py create_user calls enforce_seat_limit BEFORE any writes. S3-03: services/tenant_ai_keys.py resolves keys with precedence tenant->platform->none. 3 owner-only endpoints on /tenant/ai-keys (GET list with masked previews, PUT replace map with audit_log per-provider-change rotation events, DELETE revert to platform pool). Never logs the raw key value — regression-guarded in tests. | F76: services/plans.py (new: plan model + effective_plan + enforce_seat_limit); services/tenant_ai_keys.py (new: resolve_ai_key + normalize + summarize); server.py (GET /tenant/plan + 3 /tenant/ai-keys endpoints + backfill migration); routers/auth.py (register initializes plan fields via new_tenant_plan_fields); routers/team.py (create_user enforces seat limit) | G76: tests/test_plans_and_ai_keys.py — 38 tests (7 effective_plan, 3 trial expiry, 3 has_feature, 1 defaults, 3 enforce_seat_limit, 1 register wire, 1 bootstrap migration, 5 resolve_ai_key precedence, 2 source, 3 normalize, 1 no-secret-leak, 4 endpoint gates, 3 PUT audit + no-leak guard, 1 delete revert, 1 seat-limit BEFORE-insert order) | H76: Done | I76: P0 | J76: 2026-08-10 | K76: 2026-08-10 | L76: afbf9b8 | M76: Sprint 3: 2/5 shipped (+ 3 RBAC items TBD). Billing provider = Razorpay (India-primary). S3-01 deferred until we're ready for external integration. Follow-ups: FIX-FUP-33 (secrets manager for ai_keys), FIX-FUP-34 (provider outage transparent fallback).
A77: FIX-FUP-33 | B77: Follow-up (from FIX-005-A) | C77: (logged during S3-03) | D77: Move tenant.ai_keys to a real secrets manager | E77: tenant.ai_keys stored plain-text in Mongo. Fine for MVP, red flag on a security review. Move to AWS Secrets Manager / HashiCorp Vault / Cloudflare Secrets Store. Wrap services/tenant_ai_keys.resolve_ai_key to fetch from the secrets manager instead of the tenant doc; keep the current in-doc storage as a fallback during migration. | F77: services/tenant_ai_keys.py + new services/secrets_manager.py | G77: test: rotate key in secrets manager, verify resolve returns new value on next call | H77: Not Started | I77: P1 | M77: Sprint 5 (DevOps/security). Blocks enterprise-tier sales.
A78: FIX-FUP-34 | B78: Follow-up (from FIX-005-A) | C78: (logged during S3-03) | D78: AI provider outage transparent fallback (tenant key -> platform) | E78: When a tenant's key returns 429/500, transparently fall back to the platform pool for that request + notify the tenant. Improves reliability without exposing platform quota to abuse (rate-limit the fallback to a low ceiling per tenant/hr). | F78: core.py LLM wrappers + services/tenant_ai_keys.py | G78: test: mock 429 on tenant key, verify fallback + notification + rate-limit on fallback | H78: Not Started | I78: P2 | M78: Depends on RBAC-23 (2FA) being live so admin can rotate the key confidently after an outage.
A79: FIX-005-B | B79: Sprint 3 / Usage Quotas | C79: S3-04 | D79: Usage-quota enforcement (402 on exceed) | E79: New services/quotas.py: check_quota reads current-month usage_events aggregation, compares to plan cap from FIX-005-A. cost param lets caller pre-block a request that would push over. Fail-open on Mongo blip — quota infra failure never blocks AI. 4 resources: llm_tokens_total (sums usage_events.tokens_total), stt_minutes (sums usage_events.units where unit_type=minutes), storage_bytes (sums files.size), brain_docs (counts brain_documents). Aggregation window = current UTC calendar month, resets on 1st. guarded_llm now reads _ctx_tenant contextvar and enforces quota BEFORE taking semaphore slot — raises HTTPException(402) with structured detail {code, resource, message, usage, cap, plan}. NEW skip_quota_check kwarg bypasses check for admin key-probe (would be user-hostile). GET /tenant/usage returns every quota with usage/cap/percent/over — powers frontend dashboard. | F79: services/quotas.py (new); services/ai/llm_limits.py (guarded_llm quota check + skip_quota_check kwarg); server.py (GET /tenant/usage endpoint); routers/admin.py (probe passes skip_quota_check=True) | G79: tests/test_quotas.py — 16 tests (6 check_quota incl. unlimited/under/over/cost-projection/last-month/tenant-isolation, 2 storage + brain_docs sources, 2 status shape, 1 status_all row-per-quota, 4 guarded_llm wiring incl. fail-open, 1 endpoint) | H79: Done | I79: P1 | J79: 2026-08-10 | K79: 2026-08-10 | L79: 29d2238 | M79: Sprint 3: 3/5 shipped (S3-02, S3-03, S3-04). Only S3-01 (Razorpay billing, deferred) + 3 RBAC items (23/24/25) remain. FIX-FUP-35 logged for soft-limit warning emails (75/90/100% thresholds).
A80: FIX-FUP-35 | B80: Follow-up (from FIX-005-B) | C80: (logged during S3-04) | D80: Soft-limit warning emails at 75/90/100% quota thresholds | E80: Backend reports percent + over flag via quota_status. A scheduler task should sweep daily, compare current percent to previously-notified threshold on tenant (persist last_notified_thresholds dict), and send an email at each crossing so tenants hit the cap with warning not surprise. Templates in services/auth_emails.py. | F80: new services/quota_alerts.py + scheduler hook | G80: test: 75% threshold triggers email once, subsequent runs don't re-send unless dropped + re-crossed | H80: Not Started | I80: P2 | M80: Post-Wave-5 polish; not go-live blocker but big UX improvement.
A81: FIX-005-C | B81: Sprint 3 / Compliance | C81: RBAC-25 | D81: DPDP AI-consent tracking (India-mandatory) | E81: New services/ai_consent.py: tenant.ai_consent = {granted_at, granted_by_user_id, granted_by_email, ip, ua, version, revoked_at}. CURRENT_CONSENT_VERSION='1.0' — bump when scope changes, tenants must re-consent. has_active_consent hot-path reader. consent_status frontend shape deliberately OMITS IP/UA (audit-only). needs_reconsent flag for version-drift. require_ai_consent raises HTTPException(451 'Unavailable For Legal Reasons') with structured detail — frontend maps to consent modal. 3 endpoints: GET (any user, banner state), POST (owner grants + captures IP/UA/UA/version), DELETE (owner flips revoked_at + preserves grant history). Both mutations emit audit_log rows. Enforcement wired at guarded_llm BEFORE quota check — single tenants.find_one reused for both consent + plan-quota reads (no double round-trip). Fail-open on Mongo blip, skip_quota_check bypasses (admin probe). | F81: services/ai_consent.py (new: has_active_consent + require_ai_consent + build_grant/revoke + consent_status); services/ai/llm_limits.py (guarded_llm calls require_ai_consent BEFORE quota check, reuses tenant fetch); server.py (3 /tenant/ai-consent endpoints + AiConsentGrantInput model) | G81: tests/test_ai_consent.py — 23 tests (5 has_active_consent state matrix, 3 consent_status incl. no-IP-leak, 3 require_ai_consent, 2 build_grant, 1 build_revoke, 7 endpoint gates + audit emission, 2 guarded_llm gate + fetch reuse) | H81: Done | I81: P1 | J81: 2026-08-10 | K81: 2026-08-10 | L81: 4115624 | M81: Sprint 3: 4/5 shipped. India DPDP-blocker closed. FIX-005-D (RBAC-23 2FA + RBAC-24 ownership transfer) next — the two go together since transfer needs 2FA confirm. S3-01 (Razorpay billing) deferred. FIX-FUP-36 (email nudge on version bump) + FIX-FUP-37 (extend gate to STT/vision) logged.
A82: FIX-FUP-36 | B82: Follow-up (from FIX-005-C) | C82: (logged during RBAC-25) | D82: Consent-doc versioning UX: email nudge on version bump | E82: When CURRENT_CONSENT_VERSION bumps, consent_status flags needs_reconsent=True but nothing emails the owner. Add scheduler task that sweeps tenants where ai_consent.version < CURRENT and sends a re-consent email once per version bump. Suppress duplicate sends via last_reconsent_notified_version on tenant doc. | F82: new services/consent_alerts.py + scheduler hook + services/auth_emails.py template | G82: test: bump version, sweep sends email once per tenant, not on subsequent sweeps | H82: Not Started | I82: P2 | M82: Non-blocker; adds compliance smoothness.
A83: FIX-FUP-37 | B83: Follow-up (from FIX-005-C) | C83: (logged during RBAC-25) | D83: Extend AI consent gate to non-LLM paths (Sarvam STT/TTS + Gemini vision) | E83: guarded_llm is the choke point for LLM calls but Sarvam STT/TTS (server.py transcribe_audio_full, signup /tts /stt) and Gemini vision calls (services/tasks OCR paths) don't route through it. Extend the consent check to those code paths so all AI processing is uniformly gated. | F83: server.py transcribe_audio_full + routers/signup.py tts/stt + Gemini vision call sites | G83: test: STT call without consent returns 451; consented STT returns 200 | H83: Not Started | I83: P1 | M83: Compliance completeness — DPDP considers STT + vision as AI processing too.
A84: FIX-005-D | B84: Sprint 3 / Security + Auth | C84: RBAC-23 + RBAC-24 | D84: TOTP 2FA + tenant ownership transfer | E84: RBAC-23: pyotp-based TOTP flow. services/auth/totp.py: begin_enrollment (secret + provisioning URI for QR), confirm_enrollment (verify pending + generate 10 bcrypt-hashed backup codes returned once), verify_totp (valid_window=1 = 30s drift), consume_backup_code (single-use), disable_totp, regenerate_backup_codes (requires current TOTP not backup). 5 endpoints on /auth/2fa: enroll, confirm, verify-login, disable, regenerate-backup-codes. All emit audit_log events (two_factor_enabled/success/failure/disabled/backup_regenerated/challenge_issued). Login flow: when user.two_factor.enabled_secret set, /login returns {two_factor_required:True, challenge_token} instead of session JWT. 5-min challenge JWT encodes {sub, tenant_id, role, type=2fa_challenge}. Client calls /2fa/verify-login with challenge+code. RBAC-24: POST /auth/tenant/transfer-ownership. Owner-only inline check. Refuses self-transfer + validates target is live member. If caller has 2FA enabled, MUST supply totp_code (prevents session-theft workspace seizure); non-2FA callers still allowed but audit marks two_fa_used=false. Atomic promote+demote in memberships (target->owner, caller->sales safe default). Legacy user.role fields synced too. Audits tenant_ownership_transferred with before/after {owner_id}. | F84: services/auth/totp.py (new: pyotp-based TOTP + bcrypt-hashed backup codes); services/auth/__init__.py (exports); routers/auth.py (5 2FA endpoints + transfer-ownership + login 2FA gate + _mint_challenge/_decode_challenge helpers + 4 input models); requirements.txt (pyotp==2.10.0) | G84: tests/test_totp_and_ownership.py — 26 tests (3 enrollment flow, 4 backup codes incl. regen invalidates, 1 disable wipes, 3 is_enabled state, 2 login challenge shape, 2 challenge token roundtrip + type-guard, 5 endpoint guards, 6 ownership transfer incl. self-refuse + live-member validation + 2FA gate + atomic swap + audit) | H84: Done | I84: P1 | J84: 2026-08-10 | K84: 2026-08-10 | L84: a8da19b | M84: SPRINT 3 COMPLETE (minus S3-01 Razorpay billing, deferred). 5/5 backlog items shipped this sprint: S3-02, S3-03, S3-04 + RBAC-23, RBAC-24, RBAC-25. 3 follow-ups logged: SMS 2FA fallback (FIX-FUP-38), tenant-level enforce-2FA policy (FIX-FUP-39), Razorpay subscription rebind on transfer (FIX-FUP-40).
A85: FIX-FUP-38 | B85: Follow-up (from FIX-005-D) | C85: (logged during Sprint 3) | D85: SMS 2FA fallback + WhatsApp OTP fallback | E85: Many Indian SME employees don't use authenticator apps. Add SMS-OTP as an alternative second factor (integrate Twilio + Razorpay MSG91 or Sarvam) and/or a WhatsApp OTP path (we already have WA infra from FIX-002-A). Same user.two_factor storage, new services/auth/sms_2fa.py. | F85: services/auth/* + relevant routers | G85: test: integration with the new provider / policy | H85: Not Started | I85: P1 | M85: Post-Sprint 3 improvement.
A86: FIX-FUP-39 | B86: Follow-up (from FIX-005-D) | C86: (logged during Sprint 3) | D86: Tenant-level enforce-2FA policy | E86: Add tenant.security_policy.require_2fa_for_owners (bool) + require_2fa_for_admins. When set, login for a matching role refuses to complete without 2FA enrolled first — user is prompted to enroll before session issued. Enterprise-grade compliance ask. | F86: services/auth/* + relevant routers | G86: test: integration with the new provider / policy | H86: Not Started | I86: P2 | M86: Post-Sprint 3 improvement.
A87: FIX-FUP-40 | B87: Follow-up (from FIX-005-D) | C87: (logged during Sprint 3) | D87: Razorpay subscription rebind on ownership transfer | E87: Ownership transfer currently changes DB state only. When S3-01 lands (Razorpay integration), the transfer must also re-point the subscription billing contact to the new owner. Coupled with S3-01. | F87: services/auth/* + relevant routers | G87: test: integration with the new provider / policy | H87: Not Started | I87: P1 | M87: Post-Sprint 3 improvement.
A88: FIX-006-A | B88: Sprint 0 / Security P0 | C88: S0-01 + S0-08 + S0-09 + S0-10 | D88: Auth credential hardening (4 launch-blockers) | E88: S0-01: seed_platform_admin no longer ships hardcoded default creds. Prod (ENV=prod) refuses to boot when SUPERADMIN_EMAIL/PASSWORD missing. Existing admin hash is NEVER overwritten on restart -- refresh path requires an explicit SUPERADMIN_ALLOW_HASH_REFRESH=1 one-off flag. S0-08: login / register / switch-workspace / 2fa-verify-login / admin-login / OTP-verify (6 sites) no longer include the raw JWT in the JSON body when AUTH_RETURN_TOKEN is off. HttpOnly cookie is the source of truth. Env defaults: off in prod, on elsewhere. New login_response() helper centralises the shape. S0-09: Platform-admin tokens now signed + verified with PLATFORM_ADMIN_JWT_SECRET (falls back to JWT_SECRET when unset for dev back-compat). A compromise of the tenant JWT_SECRET can no longer forge platform-admin sessions. type='platform_admin' claim remains as second gate either way. S0-10: verify_otp invalidates invite_token + expiry on successful accept, so the invite link stops resolving on /auth/invite/{token} (no more leaked name / masked phone) and a second /auth/invite/{token}/start can't bomb the invitee's phone with fresh SMS OTPs. Records invite_consumed_at for the paper trail. | F88: config.py (PLATFORM_ADMIN_JWT_SECRET, AUTH_RETURN_TOKEN, SUPERADMIN_ALLOW_HASH_REFRESH env plumbing + env-driven defaults); core.py (create_admin_token + get_platform_admin use admin secret; new login_response() helper); server.py (seed_platform_admin prod refuse + no-silent-refresh + verify_otp invite invalidation + login_response wiring; login_response import); routers/auth.py (register + login + switch-workspace + 2fa-verify-login all route through login_response); routers/admin.py (admin_login routes through login_response) | G88: tests/test_auth_hardening.py -- 23 tests: 4 login_response helper (flag on/off/kwargs/no-shared-state); 5 AUTH_RETURN_TOKEN env semantics (prod default off, dev default on, explicit overrides, truthy/falsy accepted); 4 platform-admin secret split (fallback, distinct, admin verifies with admin secret, tenant secret cannot forge admin); 6 seed_platform_admin (prod refuses, dev fallback, env creds, hash NOT overwritten by default, opt-in refreshes, opt-in noop when password matches); 2 invite invalidation source-inspection guards; 2 no-raw-token endpoint guards (grep-style regression backstop) | H88: Done | I88: P0 | J88: 2026-08-11 | K88: 2026-08-11 | L88: c57b550 | M88: Sprint 0 batch A. 4 launch-blockers shipped together. 337 pre-existing auth/RBAC/session/plans/consent/totp tests still green (zero regressions). Deployment note for ops: set PLATFORM_ADMIN_JWT_SECRET + SUPERADMIN_EMAIL + SUPERADMIN_PASSWORD as distinct high-entropy env values before flipping ENV=prod. AUTH_RETURN_TOKEN defaults off in prod; explicitly set =1 only if a native-mobile client needs the bearer path.
A89: FIX-006-B | B89: Sprint 0 / Security P0 | C89: S0-02 | D89: Strict CORS allow-list + CSRF double-submit cookie | E89: CORS lockdown: removed allow_origin_regex='.*'+allow_credentials=True combo that echoed back any origin and let evil.com make credentialed cross-origin calls carrying the user's auth cookie. CORS_ORIGINS env is now required in prod (unset or containing '*' makes config.py raise at boot). Dev defaults to local frontend origins. CSRF (double-submit cookie): set_auth_cookie + set_admin_cookie now also set a non-HttpOnly dos_csrf cookie carrying a fresh secrets.token_urlsafe(32) token. Frontend JS reads it and echoes as X-CSRF-Token on every mutating request. New services/csrf.py middleware compares header (constant-time) to cookie on each cookie-authed mutating request. Safe verbs, exempt paths (webhooks + login), and bearer-authed requests bypass. Rollout via CSRF_ENFORCE env -- defaults OFF so this batch ships without a breaking frontend change; middleware logs match/mismatch metrics so ops watches adoption before flipping enforcement on. | F89: config.py (CORS_ORIGINS strict allow-list parser + prod boot refusal; CSRF_COOKIE_NAME/HEADER_NAME/EXEMPT_PATHS/ENFORCE env plumbing); core.py (set_csrf_cookie/clear_csrf_cookie helpers; set_auth_cookie + set_admin_cookie now mint CSRF cookie; clear paths also clear CSRF); server.py (replaced regex-CORS block with strict allow-list + CSRFMiddleware registration + startup log); services/csrf.py (new: CSRFMiddleware + _check + metrics counters) | G89: tests/test_cors_csrf.py -- 31 tests: 7 CORS parsing (prod refuses empty/wildcard/wildcard-mixed, accepts explicit list, strips whitespace/empty, dev fallback, dev override); 6 CSRF cookie minting (auth/admin sets, fresh token per call, clear also clears CSRF, explicit token); 8 check contract (safe verbs, exempt paths, bearer bypass, missing cookie/header, value mismatch, admin cookie equivalence); 3 metrics (counter shape, reset, snapshot returns copy); 4 enforce toggle parsing; 5 middleware dispatch (shadow passes, enforce 403s, matching passes, bearer bypasses, exempt-path bypasses). test_auth_hardening.py refactored to use monkeypatch.setattr on module attrs instead of importlib.reload(config) -- kills the cross-test config pollution that surfaced when TestClient closes shared asyncio loop. | H89: Done | I89: P0 | J89: 2026-08-12 | K89: 2026-08-12 | L89: ababc06 | M89: Sprint 0 batch B. 405/405 pass across adjacent auth/RBAC/session/plans/consent/totp/tenancy/dockerfile surfaces. test_workflows_dynamic excluded from regression -- pre-existing asyncio.run() vs get_event_loop() interaction is unrelated to this batch (FIX-FUP-41 logged). Deployment: set CORS_ORIGINS to comma-separated exact origins before ENV=prod. Frontend follow-up (FIX-FUP-42): read dos_csrf cookie in JS, send X-CSRF-Token header on mutating requests, then flip CSRF_ENFORCE=1 in prod once staging shows ~100% match rate.
A90: FIX-FUP-41 | B90: Follow-up (from FIX-006-B) | C90: (logged during Sprint 0) | D90: Kill test-suite asyncio-loop flakiness | E90: test_workflows_dynamic.py uses asyncio.run() which closes the shared event loop, breaking test_deprovisioning/quotas/email_verification that use asyncio.get_event_loop(). Under xdist loadscope both can land on the same worker in an order that trips this. Fix: standardize on asyncio.new_event_loop() everywhere (or asyncio.run everywhere). | F90: tests/* (FUP-41) or frontend/src/api (FUP-42) | G90: test: cross-worker asyncio stability / frontend integration | H90: Not Started | I90: P2 | M90: Post-FIX-006-B improvement.
A91: FIX-FUP-42 | B91: Follow-up (from FIX-006-B) | C91: (logged during Sprint 0) | D91: Frontend: read dos_csrf, send X-CSRF-Token, flip CSRF_ENFORCE | E91: Read the dos_csrf cookie via document.cookie (non-HttpOnly). Wrap fetch/axios to send X-CSRF-Token header on every POST/PUT/PATCH/DELETE. Watch staging csrf_check_failed logs. Once ~100% match rate, set CSRF_ENFORCE=1 in prod. Middleware will start returning 403 on mismatch. | F91: tests/* (FUP-41) or frontend/src/api (FUP-42) | G91: test: cross-worker asyncio stability / frontend integration | H91: Not Started | I91: P0 | M91: Post-FIX-006-B improvement.
A92: FIX-006-C | B92: Sprint 0 / Security P0 | C92: S0-03 + S0-04 + S0-05 | D92: Endpoint P0s (files / OTP / WhatsApp) | E92: S0-03: GET /api/files/{fname} legacy local-disk fallback is now off-by-default. The old branch served any file on disk to any authenticated caller -- no tenant-ownership check on the legacy path. Gated behind SERVE_LEGACY_LOCAL_DISK env (default False); denied hits logged for observability. S0-04: /auth/otp/request no longer surfaces dev_otp in the JSON body unless DEV_OTP_IN_RESPONSE=1 is explicitly set. server.py now refuses to boot in prod when neither APM_SMS_API_KEY nor TWILIO_* is configured -- silent dev-mode fall-through would hand working login codes to any /auth/otp/request caller. S0-05: WhatsApp webhook rejects (403) on X-Hub-Signature-256 mismatch instead of logging + processing. Also refuses missing WA_APP_SECRET in prod (dev/staging accept with WARN so local tunnels work). hmac.compare_digest preserved for constant-time compare. | F92: config.py (SERVE_LEGACY_LOCAL_DISK + DEV_OTP_IN_RESPONSE env parsing); server.py (get_file legacy-branch gate + logging; _issue_otp dev_otp gate; TWILIO/APM boot-check raise; whatsapp_webhook 403 on mismatch + prod refuses missing WA_APP_SECRET) | G92: tests/test_endpoint_hardening.py -- 14 tests: 4 legacy-disk fallback (source has gate, default off, opt-in works, tenant scope preserved on non-legacy branches); 5 dev-OTP (source gates on flag, default off, opt-in works, prod-boot check exists, end-to-end prod-without-SMS refuses to boot); 5 WhatsApp signature (rejects on mismatch not processes, constant-time compare stays, missing secret rejected in prod, not-configured branch unchanged, HMAC recomputes correctly) | H92: Done | I92: P0 | J92: 2026-08-12 | K92: 2026-08-12 | L92: 685141d | M92: Sprint 0 batch C. 419/419 pass across adjacent auth/RBAC/session/plans/consent/totp/tenancy surfaces. test_workflows_dynamic still excluded per FIX-FUP-41. Deployment: set APM_SMS_API_KEY (India) or TWILIO_* (global) before ENV=prod. Set WA_APP_SECRET whenever WhatsApp ingestion is enabled in prod. Leave SERVE_LEGACY_LOCAL_DISK unset in prod.
A93: FIX-006-D | B93: Sprint 0 / Security P0 | C93: S0-06 + S0-07 | D93: Unauth-AI rate-limit/captcha + tenant login lockout | E93: S0-06: new shared services.rate_limit.guard_unauth_ai_endpoint() extracts the 3-check pattern (hourly quota + burst quota + CAPTCHA) that signup.py already used, and applies it to the two /api/onboarding/* endpoints that were still unguarded. Both call claude_chat unauthenticated, so drive-by traffic burns real LLM credit. onboarding/os-blueprint is the biggest per-call spend on the pre-auth surface. Per-(service, kind) buckets so signup-drained quotas don't affect onboarding and vice-versa. S0-07: tenant /api/auth/login now has a 5-attempt / 15-min lockout -- parity with admin login. db.user_login_attempts keyed by (IP, email), X-Forwarded-For preferred for real client IP. Lock check runs BEFORE db.users.find_one so timing doesn't leak whether an email exists. Cool-down clears on natural expiry AND on successful login so a slow attacker can't share the cooldown with the legitimate user. Emits login_locked_out audit event. | F93: services/rate_limit.py (new public guard_unauth_ai_endpoint() with per-service, per-kind buckets + configurable quotas + require_captcha opt-out); routers/onboarding.py (import shared helper; apply guard to onboarding_suggest + onboarding_os_blueprint; both handlers gain request: Request param); routers/auth.py (LOGIN_MAX_ATTEMPTS=5, LOGIN_LOCKOUT_MIN=15 constants; _login_ident/_login_locked_out/_login_record_failure/_login_clear_attempts helpers; login endpoint wires lock check + record-on-fail + clear-on-success + audit login_locked_out event) | G93: tests/test_ratelimit_and_lockout.py -- 23 tests: 7 unauth-AI guard (first hit ok, hourly 429, burst 429, captcha required, service isolation, kind isolation, captcha opt-out); 3 endpoint wire-up guards (both onboarding endpoints call shared helper, module imports it); 7 lockout unit tests (ident shape, XFF preference, below/at threshold, window expiry clears, increment upserts, clear wipes, bad iso doesn't perma-lock); 4 login source-inspection guards (lock check before DB find, records on failure, clears on success, 429 not 401, parity numbers with admin login) | H93: Done | I93: P0/P1 | J93: 2026-08-12 | K93: 2026-08-12 | L93: 93a9f1c | M93: Sprint 0 batch D. CLOSES SPRINT 0. 442/442 pass across all adjacent auth/RBAC/session/plans/consent/totp/tenancy/dockerfile test surfaces. test_workflows_dynamic still excluded per FIX-FUP-41. Deployment: consider adding a Mongo TTL index on user_login_attempts.last (mirrors platform_login_attempts) so expired rows auto-clean -- logged as FIX-FUP-43. In prod, set CAPTCHA_REQUIRED=1 + TURNSTILE_SECRET to hard-enforce captcha on all pre-auth AI endpoints (currently permissive in dev/staging where no secret is set).
A94: FIX-FUP-43 | B94: Follow-up (from FIX-006-D) | C94: (logged during Sprint 0) | D94: TTL index on user_login_attempts.last | E94: Mirror the scheduler_locks / platform_login_attempts TTL pattern: create index on db.user_login_attempts.last with expireAfterSeconds = LOGIN_LOCKOUT_MIN * 60 * 2 (double the window so a fresh row can still exist for its full useful life). Kills row buildup for attackers who spray many (IP, email) pairs. | F94: server.py bootstrap indexes block; services/auth or routers/auth (where LOGIN_LOCKOUT_MIN is defined) | G94: test: index exists on collection after bootstrap; row inserted at T=0 gone after T=LOGIN_LOCKOUT_MIN*2 | H94: Not Started | I94: P2 | M94: Post-Sprint-0 hygiene.

Sheet Kanban Board
A1: Roadmap Kanban Board — swimlanes = Sprints, cards color-coded by Priority
A2: Snapshot view for planning. To track day-to-day status changes, edit the Task Backlog tab.
A4: Sprint 0 Critical Security & Auth (GATE) | B4: Sprint 1 Scale & Operational Blockers (GATE) | C4: Sprint 2 Tenancy Hygiene & Data Integrity (parallel) | D4: Sprint 3 Billing & Multi-Tenant AI Keys (GATE) | E4: Sprint 4 AI Brain / Agentic Enhancement (parallel) | F4: Sprint 5 DevOps, Deployment & Data Migration (GATE)
A5: [S0-01] Remove hardcoded superadmin default credentials (Security/Auth) | B5: [DONE][S1-01] Externalize the follow-up scheduler (Scale/Ops) | C5: [DONE][S2-01] Add _ensure_owned() helper (Tenancy/Data) | D5: [S3-01] Integrate real billing (Stripe or Razorpay) (Billing/AI-Keys) | E5: [S4-01] Fix text-index stemming + index db.memory (AI/Brain) | F5: [S5-01] Stand up a staging environment (DevOps/Migration)
A6: [S0-02] Fix CORS wildcard + credentials (Security/Auth) | B6: [DONE][S1-02] Index phone, drop Python-side filter (Scale/Ops) | C6: [DONE][S2-02] Complete TENANT_COLLECTIONS wipe (Tenancy/Data) | D6: [DONE][S3-02] Add plan / entitlement fields to tenant doc (Billing/AI-Keys) | E6: [S4-02] Fix task-done Brain write-coverage gap + link provenance (AI/Brain) | F6: [S5-02] Run a load test at target scale (DevOps/Migration)
A7: [S0-03] Auth-gate file downloads (Security/Auth) | B7: [DONE][S1-03] Move all uploads to obj_store (Scale/Ops) | C7: [DONE][S2-03] Tenant-scope OTP + WhatsApp phone routing (Tenancy/Data) | D7: [DONE][S3-03] Per-tenant AI key resolver (Billing/AI-Keys) | E7: [S4-03] Rename brain_contexts -> brain_query_cache (AI/Brain) | F7: [S5-03] Add observability (Sentry + structured logs + APM) (DevOps/Migration)
A8: [S0-04] Kill dev-mode OTP leak (Security/Auth) | B8: [DONE][S1-04] Commit real deployment config (Scale/Ops) | C8: [DONE][S2-04] Fix cross-tenant WhatsApp log leak (Tenancy/Data) | D8: [DONE][S3-04] Enforce usage quotas (402 on exceed) (Billing/AI-Keys) | E8: [S4-04] Unify /ask and /brain/agent retrieval reach (AI/Brain) | F8: [S5-04] Write + TEST a backup/restore runbook (DevOps/Migration)
A9: [S0-05] Fix WhatsApp signature bypass (Security/Auth) | B9: [DONE][S1-05] Timeout + concurrency-limit LLM calls (Scale/Ops) | C9: [DONE][S2-05] Fix unfiltered enrich_decisions fetch (Tenancy/Data) | E9: [S4-05] Extract + chunk + embed documents at ingest (AI/Brain) | F9: [S5-05] Data migration plan for schema changes above (DevOps/Migration)
A10: [S0-06] Rate-limit + captcha unauth AI endpoints (Security/Auth) | B10: [DONE][S1-06] Fix hardcoded purchase_payment key (Scale/Ops) | C10: [DONE][S2-06] Add session invalidation on logout/password-change (Tenancy/Data) | E10: [S4-06] Adopt vector search + hybrid retrieval (AI/Brain) | F10: [S5-06] Stand up CI/CD (DevOps/Migration)
A11: [S0-07] Add login rate limiting (Security/Auth) | C11: [DONE][S2-07] Add email verification + password reset (Tenancy/Data) | E11: [S4-07] Formalize a tool registry (AI/Brain) | F11: [S5-07] Define a rollback procedure (DevOps/Migration)
A12: [S0-08] Stop returning raw JWT in response body (Security/Auth) | C12: [DONE][S2-08] Fix dead contacts.kind index (Tenancy/Data) | E12: [S4-08] Add bounded planner-executor loop + native function-calling (AI/Brain) | F12: [S5-08] Move secrets to a real secrets manager (DevOps/Migration)
A13: [S0-09] Split JWT secret: tenant vs platform admin (Security/Auth) | C13: [DONE][S2-09] Fix denormalized-name staleness (Tenancy/Data) | E13: [S4-09] Add per-conversation agent memory (AI/Brain) | F13: [S5-09] Staged rollout plan (5 -> 20 -> 50 -> 100) (DevOps/Migration)
A14: [S0-10] Invalidate invite tokens after use (Security/Auth) | C14: [DONE][S2-10] Handle concurrent-registration race (Tenancy/Data) | E14: [S4-10] Expand Brain write coverage to finance/workflow/meetings (AI/Brain) | F14: [S5-10] Final go/no-go review (DevOps/Migration)
C15: [DONE][S2-11] Flag AI-operating-model generation failures (Tenancy/Data) | E15: [S4-11] Make tag vocabulary tenant/industry-configurable (AI/Brain)
C16: [DONE][S2-12] Fix 'active workflows' hardcoded terminal stages (Tenancy/Data)
A19: Card color = Priority:
A20: P0 — ship blocker
A21: P1 — before real customer
A22: P2 — hardening

Sheet Testing Plan
A1: Testing Plan — from automated tests through Alpha, Beta, and GA
A2: Every test type required before going live, sequenced by phase, plus the Alpha -> Closed Beta -> Staged Beta -> GA rollout milestones.
A4: Rollout Milestones
A5: Stage | B5: Tenant Count | C5: Duration | D5: Entry Criteria | E5: Exit Criteria / Pass Bar
A6: Internal Alpha | B6: 0 (internal only) | C6: 1-2 weeks | D6: Sprint 0 + 1 P0 Done, automated suite green | E6: Zero open P0/P1 after full manual walkthrough of every module + baseline load test
A7: Closed Beta | B7: 3-5 design partners | C7: 2-4 weeks | D7: Alpha exit met + Sprint 2 + 3 Done + backup/restore drill passed | E7: No P0 incidents, daily active usage from most partners, isolation matrix 100% pass, 1+ non-textile tenant validated
A8: Staged Open Beta | B8: 10 -> 30 -> 50 tenants | C8: 3-6 weeks (tiered) | D8: Closed Beta exit met + Sprint 5 Done | E8: SLO held at every tier, zero scheduler/cross-tenant incidents, support load manageable
A9: General Availability | B9: 100+ / self-serve | C9: Ongoing | D9: Staged Beta exit met + Go-Live Checklist 100% + go/no-go held | E9: Sustained SLA at target traffic, zero open P0s for a full monitoring cycle
A11: Detailed Test Plan — by phase
A12: Phase | B12: Test Type | C12: What It Verifies | D12: Scope / Method | E12: Entry Criteria | F12: Exit Criteria / Pass Bar | G12: Environment | H12: Linked Sprint | I12: Status | J12: Owner
A13: A | B13: Unit Testing | C13: Individual functions/handlers behave correctly in isolation (auth, RBAC, compute handlers, operating-model resolver, etc.) | D13: pytest, run on every PR (backend/pytest.ini, backend/tests/) | E13: Code written | F13: 100% of new/changed code has a passing unit test; suite green in CI | G13: Dev / CI | H13: Sprint 0-5 (continuous) | I13: In Progress — 279/279 offline suite green across 15 test files
A14: A | B14: Integration Testing | C14: Full request/response flow across routers + DB for each domain (auth, tasks, decisions, workflows, brain, ledger) | D14: pytest against a real test Mongo instance, one suite per router domain | E14: Unit suite green | F14: Every endpoint touched by Sprints 0-3 has at least one integration test; suite green | G14: Dev / CI | H14: Sprint 0-3 | I14: Not Started
A15: A | B15: Regression Testing | C15: Nothing that used to work broke as a result of this round of fixes | D15: Full automated suite re-run after each sprint merges to the branch | E15: Each sprint's tasks marked Done | F15: Zero net-new failures vs. the pre-sprint baseline run | G15: CI | H15: Every sprint | I15: In Progress — 279/279 offline suite green across 15 test files
A16: B | B16: Multi-Tenant Isolation Test Matrix | C16: No cross-tenant read/write is possible on ANY collection, endpoint, or background job | D16: Scripted test: create 2+ tenants with overlapping data (incl. same phone number per S2-03), attempt cross-tenant read/write/delete on every collection + every _ensure_owned call site from S2-01 | E16: Sprint 2 tasks Done | F16: 100% pass — zero cross-tenant access possible, incl. OTP/WhatsApp phone routing and tenant deletion completeness | G16: Staging | H16: Sprint 2 | I16: Not Started
A17: B | B17: Dynamic-Workflow Multi-Tenant Test | C17: A NON-textile tenant (e.g. restaurant/clinic) gets a correctly working approval + payment-tracking loop, not just the textile demo | D17: Onboard a synthetic non-textile tenant, run its AI-designed pipeline end to end incl. owner approval + dashboard KPIs | E17: S1-06 Done | F17: Approval gate, pending-purchases dashboard, and payment-overdue alerts all fire correctly for the non-textile pipeline | G17: Staging | H17: Sprint 1 | I17: Not Started
A18: C | B18: Security / Penetration Testing | C18: Every Sprint 0 vulnerability is actually closed, not just patched in one spot | D18: Manual + tool-assisted (OWASP ZAP or similar): CORS/CSRF exploit attempt, unauth file access, JWT tampering, WhatsApp signature bypass, brute-force login, superadmin default creds | E18: Sprint 0 tasks Done | F18: Zero exploitable findings on the Sprint 0 issue list; independent reviewer (or external pentest) sign-off | G18: Staging | H18: Sprint 0 | I18: Not Started
A19: C | B19: RBAC / Permission Audit | C19: Every role sees exactly what it should and nothing more (finance data, admin routes, brain visibility rules) | D19: Scripted test matrix: role x endpoint x expected access, incl. brain_rbac intents and document visibility rules | E19: Sprint 0-2 Done | F19: 100% pass on the role x endpoint matrix | G19: Staging | H19: Sprint 0-2 | I19: Not Started
A20: D | B20: Load / Performance Testing — Baseline | C20: Normal-traffic response times meet SLO before adding concurrency | D20: k6 or Locust against staging, single-tenant, ramping requests per endpoint | E20: Sprint 1 Done, staging live (S5-01) | F20: P95 latency within target (e.g. <500ms for reads, <3s for AI-backed endpoints) at expected steady load | G20: Staging | H20: Sprint 5 | I20: Not Started
A21: D | B21: Load Testing — Multi-Tenant Concurrency | C21: The system holds up with ~100 tenants' worth of simultaneous traffic, not just one tenant at a time | D21: k6/Locust simulating 100 tenants concurrently hitting dashboards, /ask, and voice-capture together (S5-02) | E21: Baseline load test passed | F21: No error-rate spike, no shared-LLM-key 429 cascade (validates S1-05), DB pool holds under SUMMED load | G21: Staging | H21: Sprint 5 | I21: Not Started
A22: D | B22: Spike / Burst Testing | C22: A sudden burst (e.g. many tenants' morning login + voice-capture rush) doesn't cascade into an outage | D22: Short high-intensity burst against the follow-up-scheduler window and login/OTP path | E22: Multi-tenant load test passed | F22: System recovers within target time with no dropped requests beyond configured rate limits | G22: Staging | H22: Sprint 5 | I22: Not Started
A23: D | B23: Soak / Endurance Testing | C23: No slow memory leak, connection-pool exhaustion, or gradual degradation over sustained runtime | D23: Run realistic traffic continuously for 24-48h on staging | E23: Spike test passed | F23: No degradation in latency/error-rate/memory over the full run | G23: Staging | H23: Sprint 5 | I23: Not Started
A24: D | B24: Database Query Performance at Volume | C24: Indexes actually get used and stay fast as data grows, not just at demo-tenant scale | D24: Seed staging with ~50k tasks / 10k contacts / 20k invoices across many tenants; profile the hot dashboard + /ask queries | E24: Schema fixes (S2-08, SCALE items) Done | F24: No full-collection scans on hot paths; dashboard/brief load within SLO at seeded volume | G24: Staging | H24: Sprint 1-2 | I24: Not Started
... A33: J | B33: General Availability / Self-Serve Launch | C33: The product is ready for unassisted signup at the full target scale | D33: Open self-serve signup; remove any beta gating | E33: Staged Beta exit criteria met; Go-Live Checklist 100% TRUE; final go/no-go held (S5-10) | F33: Sustained SLA at ~100-tenant traffic with no open P0s for a full monitoring cycle | G33: Production | H33: After Sprint 5 | I33: Not Started
A35: Phase key:
A36: A | B36: Automated (Unit/Integration/Regression)
A37: B | B37: Multi-Tenant Isolation
A38: C | B38: Security / Pentest
A39: D | B39: Load & Performance
A40: E | B40: Resilience / Concurrency / Chaos
A41: F | B41: Migration & Backup/DR
A42: G | B42: Internal Alpha
A43: H | B43: Closed Beta
A44: I | B44: Staged Open Beta
A45: J | B45: General Availability

Sheet RBAC & People Access
A1: RBAC & People Access — Product-Level Audit
A2: Deep audit of who-can-do-what across DecisionOS. Written product-developer style: map the current model, catalog every gap that stops the product from being sold to a multi-employee SME, ship each gap as a tracked task with tests. Companion to Sprint 2 (which fixed tenancy plumbing); this tab covers the human-facing layer on top.
A4: 1. Current-state model — what exists TODAY (verified in code)
A6: Core primitives (backend/core.py)
A7: # | B7: Primitive | C7: What it does | D7: Evidence (file:line) | E7: Verdict | I7: Notes
A8: 1 | B8: require_role(*roles) | C8: FastAPI dependency; 403 unless user.role in roles. | D8: core.py:347 | E8: OK | I8: Simple, works. Only 8 endpoints use it.
A9: 2 | B9: require_perm(perm) | C9: FastAPI dependency; 403 unless perm in user_perms(user). | D9: core.py:384 | E9: OK | I9: Only ~35 route uses; most endpoints use bare get_current_user.
A10: 3 | B10: user_perms(user) | C10: Owner -> ALL permission keys. Else user.permissions[] (if set) filtered to known keys. Else ROLE_DEFAULT_PERMS.get(role, _BASE_PERMS). | D10: core.py:364-370 | E10: WEAK | I10: Owner is a magic god-role. No way to say 'owner minus finance'.
A11: 4 | B11: _BASE_PERMS | C11: {inbox, data_input, people, workflows, tasks, brain, ask} — 7 keys. | D11: core.py:357 | E11: OK | I11: Sane starter set.
A12: 5 | B12: ROLE_DEFAULT_PERMS | C12: Maps only 'sales' -> _BASE_PERMS and 'finance' -> _BASE_PERMS | {finance, ledger}. No entry for 'production', 'operations', or any custom role — they all silently fall through to _BASE_PERMS. | D12: core.py:358-361 | E12: GAP | I12: Custom roles created via /tenant/roles have NO way to add perms without editing each user.
A13: 6 | B13: PERMISSION_KEYS | C13: 14 keys: inbox, voice_capture, data_input, people, finance, ledger, workflows, tasks, brain, ask, approvals, decisions_approve, leave_approve, team_manage. | D13: config.py:38-42 | E13: OK | I13: Reasonable granularity. But 'approvals', 'leave_approve', 'inbox', 'tasks', 'ledger' are unused as decorators.
A14: 7 | B14: ROLES vs DEFAULT_ROLES | C14: config.ROLES = [owner, sales, production, finance]. DEFAULT_ROLES = [sales, operations, finance]. Mismatch: 'production' vs 'operations'. | D14: config.py:36, 44-48 | E14: BUG | I14: Silent inconsistency — tenants get 'operations' but permission logic expects 'production'.
A16: Identity + membership model
A17: # | B17: Aspect | C17: What exists | D17: Evidence | E17: Verdict | I17: SaaS impact
A18: 1 | B18: User-to-tenant link | C18: Single `tenant_id` field on user doc. No memberships collection. | D18: team.py:143 | E18: GAP | I18: One user = one workspace. Accountants/consultants who serve multiple SMEs cannot exist as a single user account — must register N times with N emails.
A19: 2 | B19: Email uniqueness | C19: Globally unique — find_one({'email': email}) with no tenant_id in the check. | D19: team.py:122, auth.py:136, signup.py:106 | E19: GAP | I19: Blocks multi-tenant membership. Same anti-pattern we JUST fixed for phones (FIX-003-A). Email needs the same treatment.
A20: 3 | B20: Passwordless (OTP-only) users | C20: Empty password -> random hash + passwordless=True; phone >= 10 digits required; OTP-only login enforced downstream. | D20: team.py:126-136, auth.py:398/487/525 | E20: OK | I20: Good for field employees without email discipline.
A21: 4 | B21: Invite tokens | C21: invite_token + invite_expires_at (+7d) written on user creation if phone given; regeneration endpoint. | D21: team.py:154-157, 169 | E21: OK | I21: But: no 'accepted' vs 'pending' state tracking, and invited users are already listed in /users same as active ones (no visible pending state to admin).
A22: 5 | B22: Suspension flags | C22: user.suspended + tenant_suspended; both checked in get_current_user -> 403. | D22: core.py:341-342 | E22: OK | I22: But there's no session revocation on suspend — the token stays cryptographically valid until it expires (though get_current_user WILL 403 next request). Combine with FIX-003-C's jti revocation.
A23: 6 | B23: Platform admin | C23: Completely separate auth system (platform_admins collection, separate JWT type, cookie name). | D23: core.py:240-277, admin.py | E23: OK | I23: Good separation. But: platform admins can do cross-tenant reclassify/delete — no super-audit trail visible.
A25: Tenant-level custom roles
A26: # | B26: Aspect | C26: What exists | D26: Evidence | E26: Verdict | I26: SaaS impact
A27: 1 | B27: Custom role CRUD | C27: POST/rename/DELETE roles per tenant via /api/tenant/roles. Structure {key, label}. 'owner' key reserved. delete_role blocks if users still assigned. | D27: server.py:1759 (add), 1775 (rename), 1794 (delete) | E27: OK | I27: Good baseline.
A28: 2 | B28: Per-role permission map | C28: NONE. Custom roles get whatever ROLE_DEFAULT_PERMS.get(key) returns (miss -> _BASE_PERMS). | D28: core.py:369 | E28: GAP | I28: Creating a 'warehouse_manager' role and expecting it to see finance requires editing EACH user's permissions[] override. No way to say 'this ROLE always gets finance perm'.
A29: 3 | B29: Per-user permission override | C29: user.permissions[] takes precedence over role defaults. clean_perms filters to known keys. | D29: core.py:365-370, 373-381 | E29: OK | I29: Fine as an escape hatch, but shouldn't be the ONLY way to grant a permission.
A31: 2. Gap findings — ranked by severity
A32: Endpoint enforcement + data-model gaps that would embarrass us with a multi-employee SME customer.
A34: A. Endpoint enforcement gaps (from 211-endpoint sweep)
A35: # | B35: Severity | C35: Endpoint / area | D35: Current gate | E35: Why it's bad | H35: Evidence | I35: Fix task
A36: A1 | B36: P0 | C36: GET /onboarding/draft/{draft_id} + PATCH | D36: Public — no auth | E36: Any client can guess a draft ID and read/write another founder's onboarding data (industry, description, roles, phone). draft_id is a UUID but there's zero enumeration protection. | H36: onboarding.py:146, 156 | I36: RBAC-01
A37: A2 | B37: P0 | C37: POST /register | D37: Public, no CAPTCHA | E37: Anyone can spin up unlimited tenants. AI credit burn + storage cost + noisy dashboard. | H37: auth.py:96 | I37: RBAC-02
A38: A3 | B38: P0 | C38: POST /website-intel + /signup/tts + /signup/stt | D38: Public | E38: Server-side URL fetch (SSRF potential) + unauthenticated AI calls burning credits. Any attacker can drain quota. | H38: signup.py:125, tts, stt | I38: RBAC-03
A39: A4 | B39: P1 | C39: POST /workflows (create) | D39: Auth-only | E39: Any employee can create workflows. But DELETE /workflows/{id} requires owner. Asymmetric. | H39: server.py:2484 vs 2596 | I39: RBAC-04
A40: A5 | B40: P1 | C40: POST /captures/{cid}/approve|reject|reassign|patch | D40: Auth-only | E40: Approving a captured draft turns it into real workflow/task data. Should be role/perm-gated. | H40: server.py:5167-5211 | I40: RBAC-05
A41: A6 | B41: P1 | C41: POST /follow-up/run | D41: Auth-only | E41: Any employee can trigger a full tenant follow-up sweep (LLM cost, notification spam). | H41: server.py:3205 | I41: RBAC-06
A42: A7 | B42: P1 | C42: 17/17 endpoints in routers/tasks.py | D42: Auth-only | E42: Reassign, DELETE execution-plan, prioritize (LLM), bulk delete — all open to every logged-in user. Inline `role!=owner` check only on /tasks/{id} DELETE. | H42: tasks.py all | I42: RBAC-07
A43: A8 | B43: P1 | C43: POST /voice-notes text/audio + /meetings audio | D43: Auth-only | E43: Every employee can burn STT/LLM credits without any quota. Voice notes attach to any task by id. | H43: server.py:2141, 2161 | I43: RBAC-08
A44: A9 | B44: P1 | C44: POST /leaves/{id}/approve|reject|request-info | D44: Auth-only + inline helper | E44: Decorator gives no auth signal at endpoint level — reviewers reading the route can't tell what's gated. Move to require_perm('leave_approve'). | H44: team.py:322, 328, 335 | I44: RBAC-09
A45: A10 | B45: P2 | C45: POST /brain/export | D45: perm(ask) | E45: 'ask' is the QUERY permission. Export = bulk data extraction, higher privilege. | H45: brain.py:64 | I45: RBAC-10
A46: A11 | B46: P2 | C46: POST /memory (create) | D46: Auth-only | E46: Any employee can insert into shared tenant memory. No 'memory_write' permission. | H46: server.py:3264 | I46: RBAC-11
A48: B. Data-model gaps (multi-workspace membership + role granularity)
A49: # | B49: Severity | C49: Finding | D49: Current behavior | E49: Product impact | H49: Evidence | I49: Fix task
A50: B1 | B50: P0 | C50: One email = one workspace | D50: users.email is globally unique. | E50: An accountant serving 5 SMEs must register 5 emails. Founders switching between their bakery + consulting workspace must log out/in. Standard SaaS SME buyers reject this. | H50: team.py:122, auth.py:136 | I50: RBAC-12
A51: B2 | B51: P0 | C51: No memberships table | D51: user.tenant_id is a single foreign key. | E51: Blocks (B1) permanently. Cannot model 'is member of Tenant A as employee + Tenant B as owner'. Every fix downstream (invite, delete, list users) must be rewritten later — cheaper to do now. | H51: team.py:143 + all users.find_one users | I51: RBAC-13
A52: B3 | B52: P1 | C52: Custom roles cannot have permissions | D52: ROLE_DEFAULT_PERMS is hardcoded to sales + finance only. | E52: Founder creates 'warehouse_manager' role, must then edit each user's permissions[] individually. Role loses its meaning as a policy unit. | H52: core.py:358-361 | I52: RBAC-14
A53: B4 | B53: P1 | C53: Owner is a magic god-role | D53: user_perms shortcuts owner to ALL permission keys. | E53: Cannot have 'Co-founder with everything EXCEPT finance visibility' — a common early-stage founder ask. No 'break-glass' pattern (grant admin temporarily, log it). | H53: core.py:365 | I53: RBAC-15
A54: B5 | B54: P1 | C54: config.ROLES / DEFAULT_ROLES mismatch | D54: 'production' in ROLES, 'operations' in DEFAULT_ROLES. | E54: Any code that switches on ROLES silently misses tenants who got 'operations' as a default role. | H54: config.py:36 vs 44-48 | I54: RBAC-16
A55: B6 | B55: P1 | C55: No pending vs accepted invite state | D55: invite_token exists but /users returns invited users same as active. No 'pending_invite' flag on the user. | E55: Admin cannot see 'you invited 3 people, 1 has accepted, 2 are pending'. Also blocks off-boarding: cannot uninvite before accept. | H55: team.py:158-165, GET /users | I55: RBAC-17
A56: B7 | B56: P2 | C56: No department / branch scope | D56: A Finance Manager in Store A sees Store B's data. | E56: Multi-branch SMEs are common in India (kirana chains, salon franchises). Blocks selling to any tenant with >1 physical location. | H56: N/A (missing entirely) | I56: RBAC-18
A57: B8 | B57: P2 | C57: No user groups | D57: Permissions attach only to (role) + (user override). | E57: Cannot say 'all Regional Managers get inventory perm' — must edit 12 individual users. | H57: N/A (missing entirely) | I57: RBAC-19
A59: C. Missing SaaS RBAC surface area (product-developer view)
A60: # | B60: Severity | C60: Missing capability | D60: Why an SME buyer expects it | H60: Precedent | I60: Fix task
A61: C1 | B61: P0 | C61: Immutable audit log (who-did-what) | D61: SOC2/DPDP/GDPR compliance + 'who deleted this decision?' operational forensics. Today log_activity is human-readable free text, not queryable, and can be deleted with a normal update. | H61: Standard in QuickBooks / Zoho One / Odoo. | I61: RBAC-20
A62: C2 | B62: P0 | C62: Session management UI (/me/sessions) | D62: User needs to see 'I'm logged in on 3 devices, revoke the phone I lost'. Backend has FIX-003-C jti revocation infra — no UI endpoint exposes it. | H62: Every consumer + B2B tool for 10 years. | I62: RBAC-21
A63: C3 | B63: P0 | C63: Off-boarding workflow (deprovisioning) | D63: Departing employee must: revoke all sessions, reassign owned tasks, transfer decisions in-flight, mark authored contacts as reassigned, revoke invite tokens. Today only role-change/suspend/delete exist — the cleanup is manual. | H63: Enterprise-must-have; SMEs benefit too. | I63: RBAC-22
A64: C4 | B64: P1 | C64: MFA (TOTP / SMS second factor) | D64: Insurance, banking-adjacent, finance-team users demand it. Also 'sign-in from a new device' second-factor. | H64: Universal. | I64: RBAC-23
A65: C5 | B65: P1 | C65: Ownership transfer flow | D65: Founder leaves the company. Today, delete owner blocks 'last owner'; there's no clean promote-then-demote sequence with tenant billing rebind. | H65: Common at series-A/B. | I65: RBAC-24
A66: C6 | B66: P1 | C66: Consent tracking for AI features | D66: DPDP-2023 requires explicit consent for AI processing of PII. Today the app just sends employee names/tasks to Anthropic without a per-tenant consent gate. | H66: Legal requirement for India. | I66: RBAC-25
A67: C7 | B67: P2 | C67: Approval delegation ('acting-as') | D67: On-leave approvers block the workflow. Should be able to say 'while I'm out, X approves for me'. FIX-001-D and team.py have plumbing but no delegation surface. | H67: Standard in HRIS / procurement. | I67: RBAC-26
A68: C8 | B68: P2 | C68: Time-bounded elevated permissions | D68: Contractor gets finance perm for month-end close, auto-revokes at end of month. Today it's manual add/remove. | H68: Nice-to-have. | I68: RBAC-27
A69: C9 | B69: P2 | C69: SSO (Google / Microsoft / SAML) | D69: Enterprise gate. Most SMEs don't ask, but any 50+ employee prospect will. | H69: SAML for enterprise; Google/MS OAuth for SME. | I69: RBAC-28
A70: C10 | B70: P2 | C70: Per-user API keys | D70: Programmatic access (Zapier, custom scripts). Today the only path is JWT extraction from a browser session. | H70: Standard. | I70: RBAC-29
A71: C11 | B71: P2 | C71: Client / customer read-only portal | D71: Share a workflow status with a customer without giving them a full account. Common ask from procurement flow. | H71: Common for procurement / support tools. | I71: RBAC-30
A73: 3. New backlog items (RBAC-01 through RBAC-30)
A74: Each row is a shippable task. Priority = same P0/P1/P2 scale as Task Backlog. Effort = S(<1d) / M(1-3d) / L(1w+). Blocks-Go-Live = whether the item must ship before we sell to a real multi-employee SME.
A76: ID | B76: Priority | C76: Effort | D76: Task title | E76: Blocks? | F76: Depends on | G76: Category | H76: Sprint | I76: Description + acceptance
A77: RBAC-01 | B77: P0 | C77: S | D77: Auth-gate onboarding drafts | E77: Yes | F77: - | G77: Endpoint gate | H77: Sprint 2.5 | I77: GET/PATCH /onboarding/draft/{draft_id} become 'signed link only': add a signed HMAC on the draft URL (draft_id + issued_at + signature). Only the client that created the draft can read/write. Add rate-limit per IP. Accept: cannot access another draft even with a leaked UUID.
A78: RBAC-02 | B78: P0 | C78: M | D78: CAPTCHA + IP rate-limit on /register | E78: Yes | F78: - | G78: Endpoint gate | H78: Sprint 2.5 | I78: Turnstile (Cloudflare, free) or hCaptcha on POST /register. IP rate limit: 3 registrations/hour/IP. Accept: bot creating 100 tenants gets blocked at #4.
A79: RBAC-03 | B79: P0 | C79: M | D79: Auth-gate + rate-limit signup AI endpoints | E79: Yes | F79: - | G79: Endpoint gate | H79: Sprint 2.5 | I79: /website-intel, /signup/tts, /signup/stt need: CAPTCHA on first call per IP + per-IP 10-req/hour ceiling. SSRF guard on /website-intel (block private IP ranges, allowlist protocols). Accept: unauth attacker cannot burn > $0.10 of AI credit.
A80: RBAC-04 | B80: P1 | C80: S | D80: Symmetric role gate on /workflows create+delete | E80: No | F80: - | G80: Endpoint gate | H80: Sprint 2.5 | I80: POST /workflows: add require_perm('workflows') at minimum, ideally require_perm('workflow_create') if we split it. Accept: employee without workflow perm gets 403 on create.
A81: RBAC-05 | B81: P1 | C81: S | D81: Gate /captures approve/reject/reassign | E81: No | F81: - | G81: Endpoint gate | H81: Sprint 2.5 | I81: Approving/rejecting a capture creates real records — must be require_perm('approvals') or role-gated. Accept: employee without approvals perm gets 403.
A82: RBAC-06 | B82: P1 | C82: S | D82: Gate /follow-up/run to owner or team_manage | E82: No | F82: - | G82: Endpoint gate | H82: Sprint 2.5 | I82: Manual follow-up trigger burns LLM. Restrict to owner or perm(team_manage).
A83: RBAC-07 | B83: P1 | C83: M | D83: Role gates across tasks router | E83: No | F83: - | G83: Endpoint gate | H83: Sprint 2.5 | I83: 17 endpoints in routers/tasks.py are auth-only. Group: reassign + priority-change + delete-execution-plan need perm('team_manage'); prioritize (LLM) needs perm('tasks'). Add explicit decorators. Accept: cross-role matrix test passes.
A84: RBAC-08 | B84: P1 | C84: S | D84: Gate voice/meeting AI on perm(voice_capture) | E84: No | F84: - | G84: Endpoint gate | H84: Sprint 2.5 | I84: voice_capture permission exists in PERMISSION_KEYS but only used by 3 endpoints. Add to /voice-notes text+audio and /meetings audio. Accept: perm-less employee can't burn STT credits.
A85: RBAC-09 | B85: P1 | C85: S | D85: Add decorator gate to leaves approve/reject | E85: No | F85: - | G85: Endpoint gate | H85: Sprint 2.5 | I85: Move inline _can_approve_leave into require_perm('leave_approve'). Keep inline check as defense-in-depth. Accept: reviewer reading the route sees the gate in the signature.
A86: RBAC-10 | B86: P2 | C86: S | D86: Split brain export permission | E86: No | F86: - | G86: Endpoint gate | H86: Sprint 2.5 | I86: POST /brain/export requires perm('brain_export') (new key) instead of perm('ask'). Accept: user with 'ask' but not 'brain_export' gets 403.
A87: RBAC-11 | B87: P2 | C87: S | D87: Gate memory write on perm(brain) | E87: No | F87: - | G87: Endpoint gate | H87: Sprint 2.5 | I87: POST /memory is auth-only. Restrict to perm('brain'). Accept: memory list still readable by all, write gated.
... A106: RBAC-30 | B106: P2 | C106: L | D106: Client/customer read-only portal | E106: No | F106: - | G106: UX | H106: Sprint 5 | I106: Share a workflow (procurement order, complaint) with an external email via a signed link. Recipient sees status timeline + can add comments, no login. Accept: customer email link opens read-only page; commenting works without account.
A108: 4. Test matrix — every RBAC item's exit criteria
A109: The test SHAPE we owe alongside each backlog item. Unit tests + integration tests + cross-role matrix.
A111: # | B111: Test type | C111: What it verifies | D111: Scope | E111: Backlog items covered | I111: Exit criteria
A112: T1 | B112: Cross-role permission matrix | C112: Every endpoint x every default role = expected 200/403. Parameterize via a role_endpoint_matrix.json fixture. | D112: All routers | E112: RBAC-04..11, 14, 15, 16 | I112: 100% pass on the matrix. New route = new row in the matrix (enforced by a test that greps for @router decorators).
A113: T2 | B113: Multi-tenant membership integration test | C113: Same email registered in 2 tenants can list both workspaces, switch, and see only that workspace's data. | D113: auth + team | E113: RBAC-12, 13 | I113: Test creates user X in tenant A and B, verifies /me/workspaces returns both, /tasks in A does not leak B.
A114: T3 | B114: Invite lifecycle test | C114: Invite -> pending -> accept -> active. Also: invite -> revoke -> cannot verify. Also: invite expiry. | D114: auth | E114: RBAC-17 | I114: All 3 paths pass.
A115: T4 | B115: Draft-URL signing test | C115: Guessing a draft_id without the signature = 401. Correct signature = 200. Expired signature = 401. | D115: onboarding | E115: RBAC-01 | I115: All 3 cases + rate-limit test.
A116: T5 | B116: CAPTCHA/rate-limit test | C116: 11th register call from same IP in an hour = 429. CAPTCHA missing = 401. | D116: register + signup AI | E116: RBAC-02, 03 | I116: Bot simulation blocked at expected threshold.
A117: T6 | B117: SSRF guard test | C117: /website-intel called with private-IP URL (localhost, 169.254.x.x, 10.x, 192.168.x) = 400. | D117: signup | E117: RBAC-03 | I117: All private ranges blocked.
A118: T7 | B118: Audit-log append-only test | C118: Every mutating endpoint writes an audit row. Audit row cannot be updated or deleted via any API. Audit row includes before+after diff. | D118: audit_log middleware | E118: RBAC-20 | I118: Random-sampled 20 mutating endpoints all leave audit trails.
A119: T8 | B119: Session revocation UX test | C119: User with 3 sessions revokes one -> that jti gets 401 next request; other 2 still work. Revoke-all keeps current session alive. | D119: session mgmt | E119: RBAC-21 | I119: All 3 flows pass.
A120: T9 | B120: Deprovisioning idempotency test | C120: Deprovision user U. Verify: all sessions revoked, tasks reassigned, decisions transferred, contacts reassigned, invite tokens killed. Running deprovision again is a no-op. | D120: team | E120: RBAC-22 | I120: Zero owned entities remain; second call returns 'already deprovisioned' cleanly.
A121: T10 | B121: 2FA enrollment + login test | C121: Enroll -> confirm with valid TOTP -> login requires TOTP -> backup code works -> lockout after N bad TOTPs. | D121: auth | E121: RBAC-23 | I121: All 4 flows pass.
A122: T11 | B122: Consent-gate test | C122: Fresh tenant hitting /ask before consent = 403 with 'consent_required'. After consent = 200. Consent revocation blocks subsequent AI calls. | D122: AI endpoints | E122: RBAC-25 | I122: 3 states all pass.
... A124: T13 | B124: Owner-exclusion test | C124: Owner with finance in owner_exclusions gets 403 on /ledger endpoints. All other owner privileges intact. | D124: core | E124: RBAC-15 | I124: One denied endpoint + one allowed endpoint confirm behavior.
A126: 5. Sequencing — what to ship first
A127: Do NOT do 30 items in parallel. Order matters: data model changes (RBAC-12/13) unblock the endpoint gates that check them.
A129: Recommended order
A130: Wave 1 — Endpoint P0s (fast wins, no model changes) | C130: RBAC-01, 02, 03. Ships this week. Closes the obvious public exposures. ~2 days.
A131: Wave 2 — Data-model refactor (the big one) | C131: RBAC-12 + RBAC-13 together. Introduces memberships collection, moves email to per-tenant unique. ~1 week including migration + full-suite regression. BLOCKS Wave 3.
A132: Wave 3 — Endpoint P1s + role editor | C132: RBAC-04..11, 14, 15, 16, 17. Batchable. ~1 week.
A133: Wave 4 — Audit + session + off-boarding P0s | C133: RBAC-20, 21, 22. ~1 week. These are what make the product feel enterprise-safe.
...

Sheet Go-Live Checklist
A1: Final Go-Live Checklist — before selling as SaaS at scale
A2: Set Done? to TRUE only when verified, not just coded. Row 24 gives the overall verdict.
A4: Area | B4: Checklist item | C4: Verified in | D4: Done?
A5: Security | B5: All Sprint 0 P0 items closed and verified (not just coded) | C5: Sprint 0 | D5: FALSE
A6: Security | B6: Secrets rotated out of .env into a real secrets manager | C6: Sprint 5 | D6: FALSE
A7: Scale | B7: Follow-up scheduler runs as a single external job, not in-process | C7: Sprint 1 | FIX-002-D (scheduler_locks TTL leader lock, single-fire under N replicas) | D7: TRUE
A8: Scale | B8: All file uploads route through obj_store; local-disk path removed | C8: Sprint 1 | FIX-002-E (voice notes / meetings / ledger / ingestions all obj_store) | D8: TRUE
A9: Scale | B9: Real Dockerfile/Procfile committed with pinned worker count | C9: Sprint 1 | FIX-002-F (multi-stage Docker + Procfile + .dockerignore, 25 static tests) | D9: TRUE
A10: Scale | B10: LLM calls have timeouts + a concurrency limit | C10: Sprint 1 | FIX-002-B (guarded_llm: asyncio.wait_for + semaphore) | D10: TRUE
A11: Multi-tenant | B11: Dynamic workflow approval loop works for a non-textile tenant | C11: Sprint 1 | FIX-001-A + FIX-001-F (tenant_procurement_pipeline + tenant_terminal_stages) | D11: TRUE
A12: Multi-tenant | B12: OTP login + WhatsApp routing are tenant-scoped | C12: Sprint 2 | FIX-003-A (otp_codes keyed by (phone,tenant_id) + cross-tenant WA safety) | D12: TRUE
A13: Multi-tenant | B13: Tenant deletion removes ALL tenant data incl. files | C13: Sprint 2 | FIX-001-E (TENANT_COLLECTIONS wipe + obj_store delete_object) | D13: TRUE
A14: Billing | B14: Real payment provider integrated (Stripe/Razorpay) | C14: Sprint 3 | D14: FALSE
A15: Billing | B15: Per-tenant AI key isolation with usage quota enforcement | C15: Sprint 3 | FIX-005-A (afbf9b8) — services/tenant_ai_keys.resolve_ai_key + services/plans.py | FIX-005-B (29d2238) — services/quotas.py + guarded_llm enforcement + /tenant/usage endpoint | D15: TRUE
... A25: Sign-off | B25: Final go/no-go review held with the full team | C25: Sprint 5 | D25: FALSE
A27: VERDICT | B27: =IF(COUNTIF(D5:D25,"TRUE")=COUNTA(D5:D25),"GO — cleared to sell as SaaS at scale","NOT YET — "&(COUNTA(D5:D25)-COUNTIF(D5:D25,"TRUE"))&" item(s) still open")
